{
"meta":{"test_sets":[],"test_metrics":[],"learn_metrics":[{"best_value":"Min","name":"RMSE"}],"launch_mode":"Train","parameters":"","iteration_count":1000,"learn_sets":["learn"],"name":"experiment"},
"iterations":[
{"learn":[9.69243434],"iteration":0,"passed_time":0.0922941666,"remaining_time":92.20187243},
{"learn":[9.554806085],"iteration":1,"passed_time":0.104917737,"remaining_time":52.35395074},
{"learn":[9.433106476],"iteration":2,"passed_time":0.1161254758,"remaining_time":38.59236645},
{"learn":[9.302047153],"iteration":3,"passed_time":0.1275939778,"remaining_time":31.77090046},
{"learn":[9.1701559],"iteration":4,"passed_time":0.1388869112,"remaining_time":27.63849532},
{"learn":[9.066560944],"iteration":5,"passed_time":0.1619455426,"remaining_time":26.82897823},
{"learn":[8.951184069],"iteration":6,"passed_time":0.1753111967,"remaining_time":24.86914547},
{"learn":[8.847774917],"iteration":7,"passed_time":0.1865764412,"remaining_time":23.1354787},
{"learn":[8.755495857],"iteration":8,"passed_time":0.2022404104,"remaining_time":22.2689163},
{"learn":[8.671083541],"iteration":9,"passed_time":0.210548021,"remaining_time":20.84425408},
{"learn":[8.571825901],"iteration":10,"passed_time":0.220618783,"remaining_time":19.83563421},
{"learn":[8.473490678],"iteration":11,"passed_time":0.2291838925,"remaining_time":18.86947381},
{"learn":[8.392199185],"iteration":12,"passed_time":0.2380359354,"remaining_time":18.07242063},
{"learn":[8.307853968],"iteration":13,"passed_time":0.2462730019,"remaining_time":17.34465571},
{"learn":[8.222311234],"iteration":14,"passed_time":0.2544382959,"remaining_time":16.70811476},
{"learn":[8.151332851],"iteration":15,"passed_time":0.2629611522,"remaining_time":16.17211086},
{"learn":[8.068443177],"iteration":16,"passed_time":0.2711412763,"remaining_time":15.67834556},
{"learn":[7.985236999],"iteration":17,"passed_time":0.2792323884,"remaining_time":15.23367808},
{"learn":[7.913922661],"iteration":18,"passed_time":0.2877932652,"remaining_time":14.85922069},
{"learn":[7.842494134],"iteration":19,"passed_time":0.2962268006,"remaining_time":14.51511323},
{"learn":[7.781401976],"iteration":20,"passed_time":0.3046140542,"remaining_time":14.2008171},
{"learn":[7.710041585],"iteration":21,"passed_time":0.3128647799,"remaining_time":13.90826158},
{"learn":[7.64294629],"iteration":22,"passed_time":0.3209009667,"remaining_time":13.63131498},
{"learn":[7.57848672],"iteration":23,"passed_time":0.3291537353,"remaining_time":13.38558524},
{"learn":[7.528369611],"iteration":24,"passed_time":0.3386624677,"remaining_time":13.20783624},
{"learn":[7.473258349],"iteration":25,"passed_time":0.3498692841,"remaining_time":13.10664164},
{"learn":[7.416991658],"iteration":26,"passed_time":0.3610618897,"remaining_time":13.01160069},
{"learn":[7.362479573],"iteration":27,"passed_time":0.3718517374,"remaining_time":12.90856745},
{"learn":[7.317980011],"iteration":28,"passed_time":0.382526012,"remaining_time":12.80802612},
{"learn":[7.264313804],"iteration":29,"passed_time":0.3936107426,"remaining_time":12.72674734},
{"learn":[7.219239404],"iteration":30,"passed_time":0.4041176926,"remaining_time":12.63193691},
{"learn":[7.172690153],"iteration":31,"passed_time":0.4133775063,"remaining_time":12.50466956},
{"learn":[7.116683131],"iteration":32,"passed_time":0.4227459277,"remaining_time":12.38773673},
{"learn":[7.072242286],"iteration":33,"passed_time":0.4324875705,"remaining_time":12.28773509},
{"learn":[7.028602378],"iteration":34,"passed_time":0.4409243472,"remaining_time":12.15691415},
{"learn":[6.983168126],"iteration":35,"passed_time":0.449393432,"remaining_time":12.03375746},
{"learn":[6.942423194],"iteration":36,"passed_time":0.4578418075,"remaining_time":11.9162611},
{"learn":[6.895460542],"iteration":37,"passed_time":0.4667415087,"remaining_time":11.81592977},
{"learn":[6.850118397],"iteration":38,"passed_time":0.4755124202,"remaining_time":11.71711374},
{"learn":[6.813462389],"iteration":39,"passed_time":0.4845854213,"remaining_time":11.63005011},
{"learn":[6.776096201],"iteration":40,"passed_time":0.492950733,"remaining_time":11.53023788},
{"learn":[6.738746418],"iteration":41,"passed_time":0.502414774,"remaining_time":11.45984175},
{"learn":[6.706982903],"iteration":42,"passed_time":0.5114890222,"remaining_time":11.38360452},
{"learn":[6.671930675],"iteration":43,"passed_time":0.5206521603,"remaining_time":11.31235148},
{"learn":[6.632647299],"iteration":44,"passed_time":0.5297282692,"remaining_time":11.24201105},
{"learn":[6.596429783],"iteration":45,"passed_time":0.5383819898,"remaining_time":11.16557431},
{"learn":[6.557382782],"iteration":46,"passed_time":0.5493376434,"remaining_time":11.13869732},
{"learn":[6.52201545],"iteration":47,"passed_time":0.5579589209,"remaining_time":11.06618527},
{"learn":[6.491484209],"iteration":48,"passed_time":0.5678107347,"remaining_time":11.02016344},
{"learn":[6.464776331],"iteration":49,"passed_time":0.5776764173,"remaining_time":10.97585193},
{"learn":[6.424712173],"iteration":50,"passed_time":0.5874874232,"remaining_time":10.93187382},
{"learn":[6.386908729],"iteration":51,"passed_time":0.597479976,"remaining_time":10.89251956},
{"learn":[6.35329478],"iteration":52,"passed_time":0.6076425243,"remaining_time":10.85731076},
{"learn":[6.322840186],"iteration":53,"passed_time":0.6187011866,"remaining_time":10.83872819},
{"learn":[6.28514236],"iteration":54,"passed_time":0.6289108629,"remaining_time":10.8058321},
{"learn":[6.251528611],"iteration":55,"passed_time":0.6408583105,"remaining_time":10.80304009},
{"learn":[6.223104165],"iteration":56,"passed_time":0.6526369077,"remaining_time":10.7971334},
{"learn":[6.192940563],"iteration":57,"passed_time":0.6624300247,"remaining_time":10.7587773},
{"learn":[6.171689328],"iteration":58,"passed_time":0.6715692496,"remaining_time":10.71096041},
{"learn":[6.144605723],"iteration":59,"passed_time":0.6802200882,"remaining_time":10.65678138},
{"learn":[6.125533979],"iteration":60,"passed_time":0.688856065,"remaining_time":10.60386631},
{"learn":[6.099262805],"iteration":61,"passed_time":0.6972664444,"remaining_time":10.54896653},
{"learn":[6.071845883],"iteration":62,"passed_time":0.7068230807,"remaining_time":10.5125909},
{"learn":[6.045533856],"iteration":63,"passed_time":0.7163103783,"remaining_time":10.47603928},
{"learn":[6.022411212],"iteration":64,"passed_time":0.725660895,"remaining_time":10.43835287},
{"learn":[6.002210208],"iteration":65,"passed_time":0.7342417354,"remaining_time":10.39063304},
{"learn":[5.966239779],"iteration":66,"passed_time":0.7432038875,"remaining_time":10.34939145},
{"learn":[5.942676003],"iteration":67,"passed_time":0.7551973065,"remaining_time":10.35064544},
{"learn":[5.913011449],"iteration":68,"passed_time":0.7650929912,"remaining_time":10.32321123},
{"learn":[5.887357221],"iteration":69,"passed_time":0.7752229398,"remaining_time":10.29939049},
{"learn":[5.865656597],"iteration":70,"passed_time":0.7845577788,"remaining_time":10.26555178},
{"learn":[5.853221791],"iteration":71,"passed_time":0.7902562649,"remaining_time":10.18552519},
{"learn":[5.842697932],"iteration":72,"passed_time":0.8004764151,"remaining_time":10.16495393},
{"learn":[5.824102479],"iteration":73,"passed_time":0.8097618732,"remaining_time":10.13296614},
{"learn":[5.805453159],"iteration":74,"passed_time":0.8196742601,"remaining_time":10.10931587},
{"learn":[5.790265689],"iteration":75,"passed_time":0.8296482056,"remaining_time":10.08677555},
{"learn":[5.772679318],"iteration":76,"passed_time":0.8394470581,"remaining_time":10.06246279},
{"learn":[5.751945217],"iteration":77,"passed_time":0.8500552281,"remaining_time":10.04808872},
{"learn":[5.732385586],"iteration":78,"passed_time":0.8591965249,"remaining_time":10.01670885},
{"learn":[5.720963513],"iteration":79,"passed_time":0.8673308499,"remaining_time":9.974304773},
{"learn":[5.701332654],"iteration":80,"passed_time":0.8759270361,"remaining_time":9.93798699},
{"learn":[5.68418135],"iteration":81,"passed_time":0.8840614574,"remaining_time":9.897175828},
{"learn":[5.658743491],"iteration":82,"passed_time":0.8923706225,"remaining_time":9.859082661},
{"learn":[5.637884296],"iteration":83,"passed_time":0.9003674095,"remaining_time":9.818292228},
{"learn":[5.625430346],"iteration":84,"passed_time":0.9088585138,"remaining_time":9.78359459},
{"learn":[5.604593917],"iteration":85,"passed_time":0.9173263486,"remaining_time":9.7492591},
{"learn":[5.584908815],"iteration":86,"passed_time":0.9256333285,"remaining_time":9.713830217},
{"learn":[5.564670434],"iteration":87,"passed_time":0.9342164332,"remaining_time":9.681879399},
{"learn":[5.541152156],"iteration":88,"passed_time":0.9426114984,"remaining_time":9.648528933},
{"learn":[5.523276202],"iteration":89,"passed_time":0.9536813831,"remaining_time":9.642778429},
{"learn":[5.505078491],"iteration":90,"passed_time":0.9631104164,"remaining_time":9.620520533},
{"learn":[5.488575314],"iteration":91,"passed_time":0.9731249327,"remaining_time":9.604319988},
{"learn":[5.467262587],"iteration":92,"passed_time":0.9839322483,"remaining_time":9.5959844},
{"learn":[5.448989597],"iteration":93,"passed_time":0.9943046042,"remaining_time":9.583403951},
{"learn":[5.434768631],"iteration":94,"passed_time":1.007828541,"remaining_time":9.600892947},
{"learn":[5.422335116],"iteration":95,"passed_time":1.018277759,"remaining_time":9.588782228},
{"learn":[5.404258097],"iteration":96,"passed_time":1.02885303,"remaining_time":9.57787924},
{"learn":[5.387175382],"iteration":97,"passed_time":1.04001925,"remaining_time":9.572422077},
{"learn":[5.372042172],"iteration":98,"passed_time":1.050308906,"remaining_time":9.558871959},
{"learn":[5.357487431],"iteration":99,"passed_time":1.059584673,"remaining_time":9.536262056},
{"learn":[5.344008664],"iteration":100,"passed_time":1.068300405,"remaining_time":9.508931326},
{"learn":[5.325221321],"iteration":101,"passed_time":1.077436411,"remaining_time":9.485665661},
{"learn":[5.30521738],"iteration":102,"passed_time":1.085840211,"remaining_time":9.456297756},
{"learn":[5.294949176],"iteration":103,"passed_time":1.095150553,"remaining_time":9.435143226},
{"learn":[5.281726945],"iteration":104,"passed_time":1.103763548,"remaining_time":9.408270241},
{"learn":[5.272217099],"iteration":105,"passed_time":1.113039042,"remaining_time":9.38732928},
{"learn":[5.25206399],"iteration":106,"passed_time":1.122370601,"remaining_time":9.367074268},
{"learn":[5.236125617],"iteration":107,"passed_time":1.136159202,"remaining_time":9.38383341},
{"learn":[5.221775638],"iteration":108,"passed_time":1.153058906,"remaining_time":9.425463165},
{"learn":[5.211462891],"iteration":109,"passed_time":1.173486969,"remaining_time":9.494576388},
{"learn":[5.195344412],"iteration":110,"passed_time":1.185734142,"remaining_time":9.496555423},
{"learn":[5.182317855],"iteration":111,"passed_time":1.197579815,"remaining_time":9.495097102},
{"learn":[5.168740203],"iteration":112,"passed_time":1.208328672,"remaining_time":9.484845417},
{"learn":[5.152487224],"iteration":113,"passed_time":1.21856602,"remaining_time":9.470609594},
{"learn":[5.129627867],"iteration":114,"passed_time":1.229166761,"remaining_time":9.459239854},
{"learn":[5.114984578],"iteration":115,"passed_time":1.239291991,"remaining_time":9.444259655},
{"learn":[5.102231246],"iteration":116,"passed_time":1.250235092,"remaining_time":9.435534923},
{"learn":[5.086651525],"iteration":117,"passed_time":1.259437259,"remaining_time":9.413759851},
{"learn":[5.074433191],"iteration":118,"passed_time":1.269934363,"remaining_time":9.401782973},
{"learn":[5.052867947],"iteration":119,"passed_time":1.278742656,"remaining_time":9.377446141},
{"learn":[5.037267266],"iteration":120,"passed_time":1.287266864,"remaining_time":9.351302259},
{"learn":[5.026160245],"iteration":121,"passed_time":1.296339167,"remaining_time":9.329391709},
{"learn":[5.009001224],"iteration":122,"passed_time":1.304876475,"remaining_time":9.303875357},
{"learn":[4.988835084],"iteration":123,"passed_time":1.313184856,"remaining_time":9.277015596},
{"learn":[4.975261949],"iteration":124,"passed_time":1.32177618,"remaining_time":9.252433262},
{"learn":[4.965367801],"iteration":125,"passed_time":1.330721007,"remaining_time":9.230556824},
{"learn":[4.948312154],"iteration":126,"passed_time":1.339302739,"remaining_time":9.206388122},
{"learn":[4.936405339],"iteration":127,"passed_time":1.348794321,"remaining_time":9.188661314},
{"learn":[4.925550104],"iteration":128,"passed_time":1.359084934,"remaining_time":9.176457188},
{"learn":[4.908439765],"iteration":129,"passed_time":1.369312259,"remaining_time":9.163858964},
{"learn":[4.897152886],"iteration":130,"passed_time":1.379371409,"remaining_time":9.150181332},
{"learn":[4.886266369],"iteration":131,"passed_time":1.389181797,"remaining_time":9.134922727},
{"learn":[4.872493186],"iteration":132,"passed_time":1.399502611,"remaining_time":9.123073414},
{"learn":[4.862379056],"iteration":133,"passed_time":1.410203438,"remaining_time":9.113702819},
{"learn":[4.85084755],"iteration":134,"passed_time":1.420868815,"remaining_time":9.104085372},
{"learn":[4.836362306],"iteration":135,"passed_time":1.42973591,"remaining_time":9.083028131},
{"learn":[4.825002927],"iteration":136,"passed_time":1.439397373,"remaining_time":9.067152798},
{"learn":[4.816044716],"iteration":137,"passed_time":1.449563922,"remaining_time":9.054522467},
{"learn":[4.799930688],"iteration":138,"passed_time":1.459270729,"remaining_time":9.03907984},
{"learn":[4.789164926],"iteration":139,"passed_time":1.468114371,"remaining_time":9.018416853},
{"learn":[4.777400417],"iteration":140,"passed_time":1.477080249,"remaining_time":8.998666198},
{"learn":[4.767455595],"iteration":141,"passed_time":1.486450459,"remaining_time":8.981510521},
{"learn":[4.756713898],"iteration":142,"passed_time":1.495016856,"remaining_time":8.959646473},
{"learn":[4.750761588],"iteration":143,"passed_time":1.503914965,"remaining_time":8.93993896},
{"learn":[4.743395573],"iteration":144,"passed_time":1.512964716,"remaining_time":8.921274702},
{"learn":[4.734050358],"iteration":145,"passed_time":1.522233864,"remaining_time":8.904025477},
{"learn":[4.72303114],"iteration":146,"passed_time":1.531284146,"remaining_time":8.885614805},
{"learn":[4.711248584],"iteration":147,"passed_time":1.539925372,"remaining_time":8.864975793},
{"learn":[4.696504342],"iteration":148,"passed_time":1.548872671,"remaining_time":8.846245929},
{"learn":[4.692548523],"iteration":149,"passed_time":1.557512602,"remaining_time":8.825904746},
{"learn":[4.677465813],"iteration":150,"passed_time":1.567369845,"remaining_time":8.812562906},
{"learn":[4.666884382],"iteration":151,"passed_time":1.577718843,"remaining_time":8.802010386},
{"learn":[4.659332064],"iteration":152,"passed_time":1.588334487,"remaining_time":8.792936668},
{"learn":[4.646964643],"iteration":153,"passed_time":1.598396418,"remaining_time":8.780801104},
{"learn":[4.634596739],"iteration":154,"passed_time":1.608191633,"remaining_time":8.767238258},
{"learn":[4.62328906],"iteration":155,"passed_time":1.618944246,"remaining_time":8.758903485},
{"learn":[4.602830112],"iteration":156,"passed_time":1.629947488,"remaining_time":8.751883643},
{"learn":[4.592967243],"iteration":157,"passed_time":1.641141405,"remaining_time":8.745829512},
{"learn":[4.581745462],"iteration":158,"passed_time":1.651911484,"remaining_time":8.73746892},
{"learn":[4.570134286],"iteration":159,"passed_time":1.665108199,"remaining_time":8.741818044},
{"learn":[4.560021052],"iteration":160,"passed_time":1.674584273,"remaining_time":8.726560278},
{"learn":[4.540539106],"iteration":161,"passed_time":1.683427294,"remaining_time":8.708099214},
{"learn":[4.525221116],"iteration":162,"passed_time":1.692389267,"remaining_time":8.690366971},
{"learn":[4.516405875],"iteration":163,"passed_time":1.701522975,"remaining_time":8.673617115},
{"learn":[4.50407688],"iteration":164,"passed_time":1.71078816,"remaining_time":8.657624933},
{"learn":[4.49758883],"iteration":165,"passed_time":1.71983982,"remaining_time":8.640641024},
{"learn":[4.481691644],"iteration":166,"passed_time":1.728097278,"remaining_time":8.619790616},
{"learn":[4.470633977],"iteration":167,"passed_time":1.737153408,"remaining_time":8.603045448},
{"learn":[4.46437753],"iteration":168,"passed_time":1.746292052,"remaining_time":8.586797014},
{"learn":[4.451900305],"iteration":169,"passed_time":1.755064505,"remaining_time":8.56884435},
{"learn":[4.439679434],"iteration":170,"passed_time":1.76342411,"remaining_time":8.548997587},
{"learn":[4.420742684],"iteration":171,"passed_time":1.773697029,"remaining_time":8.538495001},
{"learn":[4.413391179],"iteration":172,"passed_time":1.784577314,"remaining_time":8.53089849},
{"learn":[4.400024051],"iteration":173,"passed_time":1.794472858,"remaining_time":8.518589544},
{"learn":[4.389628753],"iteration":174,"passed_time":1.804263689,"remaining_time":8.505814535},
{"learn":[4.377191732],"iteration":175,"passed_time":1.813948579,"remaining_time":8.492577439},
{"learn":[4.364966817],"iteration":176,"passed_time":1.823789594,"remaining_time":8.480106419},
{"learn":[4.360353341],"iteration":177,"passed_time":1.832556365,"remaining_time":8.462704113},
{"learn":[4.353346532],"iteration":178,"passed_time":1.843238119,"remaining_time":8.454181542},
{"learn":[4.349383832],"iteration":179,"passed_time":1.853306683,"remaining_time":8.442841556},
{"learn":[4.335681429],"iteration":180,"passed_time":1.862420015,"remaining_time":8.427193328},
{"learn":[4.314549331],"iteration":181,"passed_time":1.872292463,"remaining_time":8.415028764},
{"learn":[4.309219757],"iteration":182,"passed_time":1.88169602,"remaining_time":8.400795894},
{"learn":[4.305356046],"iteration":183,"passed_time":1.891925038,"remaining_time":8.390276256},
{"learn":[4.290340121],"iteration":184,"passed_time":1.900928564,"remaining_time":8.374360971},
{"learn":[4.282192546],"iteration":185,"passed_time":1.910079963,"remaining_time":8.359167148},
{"learn":[4.273288864],"iteration":186,"passed_time":1.918678952,"remaining_time":8.341636299},
{"learn":[4.261830815],"iteration":187,"passed_time":1.926765463,"remaining_time":8.321987002},
{"learn":[4.249219079],"iteration":188,"passed_time":1.935300529,"remaining_time":8.304384811},
{"learn":[4.237307865],"iteration":189,"passed_time":1.943386775,"remaining_time":8.284964673},
{"learn":[4.220993489],"iteration":190,"passed_time":1.951852432,"remaining_time":8.267270248},
{"learn":[4.211385605],"iteration":191,"passed_time":1.960157972,"remaining_time":8.248998132},
{"learn":[4.205675344],"iteration":192,"passed_time":1.968246831,"remaining_time":8.229923279},
{"learn":[4.196750321],"iteration":193,"passed_time":1.976562876,"remaining_time":8.211905555},
{"learn":[4.18928162],"iteration":194,"passed_time":1.989325388,"remaining_time":8.212343267},
{"learn":[4.176865943],"iteration":195,"passed_time":1.999600466,"remaining_time":8.202442728},
{"learn":[4.162510466],"iteration":196,"passed_time":2.009028988,"remaining_time":8.189087701},
{"learn":[4.147186047],"iteration":197,"passed_time":2.01725708,"remaining_time":8.170909992},
{"learn":[4.136104648],"iteration":198,"passed_time":2.026637858,"remaining_time":8.15747198},
{"learn":[4.126082394],"iteration":199,"passed_time":2.03695736,"remaining_time":8.147829441},
{"learn":[4.11052656],"iteration":200,"passed_time":2.046861494,"remaining_time":8.136529025},
{"learn":[4.094510896],"iteration":201,"passed_time":2.055705492,"remaining_time":8.121054368},
{"learn":[4.084542104],"iteration":202,"passed_time":2.065086848,"remaining_time":8.107754768},
{"learn":[4.069790216],"iteration":203,"passed_time":2.074989923,"remaining_time":8.096529309},
{"learn":[4.059044511],"iteration":204,"passed_time":2.085162901,"remaining_time":8.086363445},
{"learn":[4.050690787],"iteration":205,"passed_time":2.094855703,"remaining_time":8.074346739},
{"learn":[4.042615782],"iteration":206,"passed_time":2.103704796,"remaining_time":8.059120307},
{"learn":[4.033301775],"iteration":207,"passed_time":2.11187774,"remaining_time":8.041380624},
{"learn":[4.019245473],"iteration":208,"passed_time":2.12169703,"remaining_time":8.0299634},
{"learn":[4.016579293],"iteration":209,"passed_time":2.13026081,"remaining_time":8.013838286},
{"learn":[4.009732888],"iteration":210,"passed_time":2.138931124,"remaining_time":7.998183207},
{"learn":[4.000726956],"iteration":211,"passed_time":2.147875672,"remaining_time":7.983613345},
{"learn":[3.996356943],"iteration":212,"passed_time":2.156757392,"remaining_time":7.968864166},
{"learn":[3.984076991],"iteration":213,"passed_time":2.166037469,"remaining_time":7.955632948},
{"learn":[3.968302925],"iteration":214,"passed_time":2.174483888,"remaining_time":7.939394661},
{"learn":[3.963529904],"iteration":215,"passed_time":2.184044291,"remaining_time":7.927271873},
{"learn":[3.947359758],"iteration":216,"passed_time":2.193252841,"remaining_time":7.913903107},
{"learn":[3.939114974],"iteration":217,"passed_time":2.204529628,"remaining_time":7.907991601},
{"learn":[3.923939326],"iteration":218,"passed_time":2.215104662,"remaining_time":7.899528499},
{"learn":[3.920838418],"iteration":219,"passed_time":2.22484471,"remaining_time":7.888085792},
{"learn":[3.91465333],"iteration":220,"passed_time":2.234493744,"remaining_time":7.876337676},
{"learn":[3.912511625],"iteration":221,"passed_time":2.244396611,"remaining_time":7.865498032},
{"learn":[3.898447855],"iteration":222,"passed_time":2.254823814,"remaining_time":7.856493738},
{"learn":[3.888417421],"iteration":223,"passed_time":2.264758792,"remaining_time":7.845771531},
{"learn":[3.884305767],"iteration":224,"passed_time":2.2738448,"remaining_time":7.83213209},
{"learn":[3.870409379],"iteration":225,"passed_time":2.282943248,"remaining_time":7.818575547},
{"learn":[3.858336142],"iteration":226,"passed_time":2.292082862,"remaining_time":7.805198468},
{"learn":[3.847510354],"iteration":227,"passed_time":2.300707049,"remaining_time":7.790113341},
{"learn":[3.845425101],"iteration":228,"passed_time":2.309586072,"remaining_time":7.775942628},
{"learn":[3.830865081],"iteration":229,"passed_time":2.31829621,"remaining_time":7.761252528},
{"learn":[3.822516784],"iteration":230,"passed_time":2.327166633,"remaining_time":7.747147795},
{"learn":[3.812022878],"iteration":231,"passed_time":2.335325282,"remaining_time":7.730731968},
{"learn":[3.809834531],"iteration":232,"passed_time":2.343515604,"remaining_time":7.71449128},
{"learn":[3.793369967],"iteration":233,"passed_time":2.352173059,"remaining_time":7.69984856},
{"learn":[3.77887275],"iteration":234,"passed_time":2.360679729,"remaining_time":7.684765926},
{"learn":[3.775728105],"iteration":235,"passed_time":2.369269328,"remaining_time":7.670007484},
{"learn":[3.772919348],"iteration":236,"passed_time":2.377982922,"remaining_time":7.655700292},
{"learn":[3.770587918],"iteration":237,"passed_time":2.389795549,"remaining_time":7.651362221},
{"learn":[3.761030298],"iteration":238,"passed_time":2.400458454,"remaining_time":7.643300767},
{"learn":[3.745744542],"iteration":239,"passed_time":2.411804496,"remaining_time":7.637380905},
{"learn":[3.743781193],"iteration":240,"passed_time":2.422054202,"remaining_time":7.627963233},
{"learn":[3.733765789],"iteration":241,"passed_time":2.433107693,"remaining_time":7.621056328},
{"learn":[3.727942558],"iteration":242,"passed_time":2.444856711,"remaining_time":7.616282017},
{"learn":[3.708907481],"iteration":243,"passed_time":2.456022734,"remaining_time":7.609644208},
{"learn":[3.698462121],"iteration":244,"passed_time":2.467871786,"remaining_time":7.605074279},
{"learn":[3.678785829],"iteration":245,"passed_time":2.480290082,"remaining_time":7.602189925},
{"learn":[3.665701673],"iteration":246,"passed_time":2.49080183,"remaining_time":7.593416106},
{"learn":[3.652939272],"iteration":247,"passed_time":2.500207455,"remaining_time":7.581274218},
{"learn":[3.638637718],"iteration":248,"passed_time":2.509545756,"remaining_time":7.568951257},
{"learn":[3.635549526],"iteration":249,"passed_time":2.519046763,"remaining_time":7.55714029},
{"learn":[3.622576033],"iteration":250,"passed_time":2.528859032,"remaining_time":7.546276554},
{"learn":[3.606002648],"iteration":251,"passed_time":2.538032243,"remaining_time":7.533524277},
{"learn":[3.591974333],"iteration":252,"passed_time":2.547478364,"remaining_time":7.521606078},
{"learn":[3.581074835],"iteration":253,"passed_time":2.55676098,"remaining_time":7.50922713},
{"learn":[3.578192581],"iteration":254,"passed_time":2.566468002,"remaining_time":7.498112397},
{"learn":[3.570141408],"iteration":255,"passed_time":2.575832231,"remaining_time":7.48601242},
{"learn":[3.552899079],"iteration":256,"passed_time":2.586503841,"remaining_time":7.47771344},
{"learn":[3.540030561],"iteration":257,"passed_time":2.596295779,"remaining_time":7.466866155},
{"learn":[3.524955695],"iteration":258,"passed_time":2.605829376,"remaining_time":7.455287905},
{"learn":[3.511175801],"iteration":259,"passed_time":2.618030418,"remaining_time":7.451317345},
{"learn":[3.501219286],"iteration":260,"passed_time":2.628432052,"remaining_time":7.442188838},
{"learn":[3.492366952],"iteration":261,"passed_time":2.639396848,"remaining_time":7.434636922},
{"learn":[3.476294372],"iteration":262,"passed_time":2.650847878,"remaining_time":7.428421619},
{"learn":[3.466590563],"iteration":263,"passed_time":2.661838655,"remaining_time":7.420883524},
{"learn":[3.455195911],"iteration":264,"passed_time":2.672460681,"remaining_time":7.412296606},
{"learn":[3.444024335],"iteration":265,"passed_time":2.683146128,"remaining_time":7.40386939},
{"learn":[3.437593042],"iteration":266,"passed_time":2.691873868,"remaining_time":7.390050732},
{"learn":[3.427654515],"iteration":267,"passed_time":2.702388144,"remaining_time":7.381149707},
{"learn":[3.415522949],"iteration":268,"passed_time":2.712387859,"remaining_time":7.370838383},
{"learn":[3.407484172],"iteration":269,"passed_time":2.722140744,"remaining_time":7.359862013},
{"learn":[3.395779614],"iteration":270,"passed_time":2.730999471,"remaining_time":7.346489352},
{"learn":[3.380562236],"iteration":271,"passed_time":2.740534839,"remaining_time":7.334960893},
{"learn":[3.370022914],"iteration":272,"passed_time":2.750961188,"remaining_time":7.32581972},
{"learn":[3.355176069],"iteration":273,"passed_time":2.760434391,"remaining_time":7.314143678},
{"learn":[3.346285247],"iteration":274,"passed_time":2.769873805,"remaining_time":7.302394576},
{"learn":[3.344052758],"iteration":275,"passed_time":2.780097923,"remaining_time":7.292720639},
{"learn":[3.328942671],"iteration":276,"passed_time":2.791642988,"remaining_time":7.286490542},
{"learn":[3.316735144],"iteration":277,"passed_time":2.802606365,"remaining_time":7.278711496},
{"learn":[3.305978562],"iteration":278,"passed_time":2.813751336,"remaining_time":7.2713789},
{"learn":[3.296166789],"iteration":279,"passed_time":2.824276551,"remaining_time":7.262425417},
{"learn":[3.285527999],"iteration":280,"passed_time":2.834601585,"remaining_time":7.25294854},
{"learn":[3.274095468],"iteration":281,"passed_time":2.844915442,"remaining_time":7.24343719},
{"learn":[3.263288351],"iteration":282,"passed_time":2.85554198,"remaining_time":7.234712366},
{"learn":[3.258173402],"iteration":283,"passed_time":2.86675648,"remaining_time":7.227456478},
{"learn":[3.250941869],"iteration":284,"passed_time":2.877067202,"remaining_time":7.217905438},
{"learn":[3.238806744],"iteration":285,"passed_time":2.889431392,"remaining_time":7.213475572},
{"learn":[3.231367632],"iteration":286,"passed_time":2.899190547,"remaining_time":7.202518676},
{"learn":[3.219251157],"iteration":287,"passed_time":2.908920105,"remaining_time":7.191496927},
{"learn":[3.211695075],"iteration":288,"passed_time":2.918739002,"remaining_time":7.180703911},
{"learn":[3.199625999],"iteration":289,"passed_time":2.928354131,"remaining_time":7.169418734},
{"learn":[3.189187232],"iteration":290,"passed_time":2.938012343,"remaining_time":7.158250005},
{"learn":[3.17595149],"iteration":291,"passed_time":2.947341997,"remaining_time":7.14629498},
{"learn":[3.166226493],"iteration":292,"passed_time":2.956697907,"remaining_time":7.134421231},
{"learn":[3.154237362],"iteration":293,"passed_time":2.967856283,"remaining_time":7.126892978},
{"learn":[3.140073633],"iteration":294,"passed_time":2.979522146,"remaining_time":7.120552925},
{"learn":[3.131615252],"iteration":295,"passed_time":2.990647643,"remaining_time":7.11289169},
{"learn":[3.119678773],"iteration":296,"passed_time":3.006933286,"remaining_time":7.117421213},
{"learn":[3.109887248],"iteration":297,"passed_time":3.017197708,"remaining_time":7.107626816},
{"learn":[3.096731032],"iteration":298,"passed_time":3.027656471,"remaining_time":7.098284905},
{"learn":[3.086420891],"iteration":299,"passed_time":3.038591575,"remaining_time":7.090047009},
{"learn":[3.074882093],"iteration":300,"passed_time":3.050089818,"remaining_time":7.083098946},
{"learn":[3.07145413],"iteration":301,"passed_time":3.06236304,"remaining_time":7.077911926},
{"learn":[3.059754759],"iteration":302,"passed_time":3.071959084,"remaining_time":7.066519742},
{"learn":[3.050503968],"iteration":303,"passed_time":3.081627371,"remaining_time":7.055304771},
{"learn":[3.042859095],"iteration":304,"passed_time":3.090297322,"remaining_time":7.041825044},
{"learn":[3.04008813],"iteration":305,"passed_time":3.099147497,"remaining_time":7.028785499},
{"learn":[3.02749473],"iteration":306,"passed_time":3.107823932,"remaining_time":7.015381059},
{"learn":[3.016347559],"iteration":307,"passed_time":3.116947389,"remaining_time":7.003011666},
{"learn":[3.001890564],"iteration":308,"passed_time":3.126403131,"remaining_time":6.991406355},
{"learn":[2.994282533],"iteration":309,"passed_time":3.135517822,"remaining_time":6.979055798},
{"learn":[2.987693609],"iteration":310,"passed_time":3.144067063,"remaining_time":6.965473333},
{"learn":[2.973929516],"iteration":311,"passed_time":3.153291116,"remaining_time":6.95341118},
{"learn":[2.963441193],"iteration":312,"passed_time":3.162179959,"remaining_time":6.940631411},
{"learn":[2.952562608],"iteration":313,"passed_time":3.171469177,"remaining_time":6.928751131},
{"learn":[2.942921967],"iteration":314,"passed_time":3.180425317,"remaining_time":6.916162992},
{"learn":[2.941324366],"iteration":315,"passed_time":3.188966387,"remaining_time":6.902699395},
{"learn":[2.929974013],"iteration":316,"passed_time":3.199373974,"remaining_time":6.893288404},
{"learn":[2.920269383],"iteration":317,"passed_time":3.208987357,"remaining_time":6.882167853},
{"learn":[2.918620477],"iteration":318,"passed_time":3.218329463,"remaining_time":6.870477631},
{"learn":[2.909276079],"iteration":319,"passed_time":3.227905872,"remaining_time":6.859299977},
{"learn":[2.896452074],"iteration":320,"passed_time":3.238102264,"remaining_time":6.849443729},
{"learn":[2.887155131],"iteration":321,"passed_time":3.247425422,"remaining_time":6.837746696},
{"learn":[2.873263691],"iteration":322,"passed_time":3.256324738,"remaining_time":6.825175999},
{"learn":[2.859912597],"iteration":323,"passed_time":3.265779665,"remaining_time":6.813787201},
{"learn":[2.850594386],"iteration":324,"passed_time":3.275738136,"remaining_time":6.803456129},
{"learn":[2.83933601],"iteration":325,"passed_time":3.286268537,"remaining_time":6.794309797},
{"learn":[2.830934141],"iteration":326,"passed_time":3.294923154,"remaining_time":6.781294442},
{"learn":[2.829427184],"iteration":327,"passed_time":3.3034012,"remaining_time":6.767943922},
{"learn":[2.82708858],"iteration":328,"passed_time":3.31219349,"remaining_time":6.755263926},
{"learn":[2.815691785],"iteration":329,"passed_time":3.320978072,"remaining_time":6.742591843},
{"learn":[2.804458934],"iteration":330,"passed_time":3.32919955,"remaining_time":6.728805133},
{"learn":[2.801851598],"iteration":331,"passed_time":3.337670548,"remaining_time":6.715553995},
{"learn":[2.800405643],"iteration":332,"passed_time":3.346179675,"remaining_time":6.702407938},
{"learn":[2.79065984],"iteration":333,"passed_time":3.354843031,"remaining_time":6.689597181},
{"learn":[2.78165081],"iteration":334,"passed_time":3.362962299,"remaining_time":6.67573113},
{"learn":[2.779823626],"iteration":335,"passed_time":3.371960204,"remaining_time":6.663635641},
{"learn":[2.777895195],"iteration":336,"passed_time":3.380866293,"remaining_time":6.6513779},
{"learn":[2.762013973],"iteration":337,"passed_time":3.389914153,"remaining_time":6.63941766},
{"learn":[2.752201968],"iteration":338,"passed_time":3.399890173,"remaining_time":6.629284378},
{"learn":[2.740736767],"iteration":339,"passed_time":3.410398087,"remaining_time":6.620184521},
{"learn":[2.738729794],"iteration":340,"passed_time":3.421600977,"remaining_time":6.612419483},
{"learn":[2.728782844],"iteration":341,"passed_time":3.433264858,"remaining_time":6.605521277},
{"learn":[2.718440946],"iteration":342,"passed_time":3.44554006,"remaining_time":6.599766238},
{"learn":[2.709585323],"iteration":343,"passed_time":3.456261982,"remaining_time":6.591011221},
{"learn":[2.69946493],"iteration":344,"passed_time":3.468211752,"remaining_time":6.584575936},
{"learn":[2.69264845],"iteration":345,"passed_time":3.479242331,"remaining_time":6.576371342},
{"learn":[2.683922367],"iteration":346,"passed_time":3.48839415,"remaining_time":6.564614928},
{"learn":[2.682721872],"iteration":347,"passed_time":3.498411859,"remaining_time":6.554495781},
{"learn":[2.675696139],"iteration":348,"passed_time":3.508130258,"remaining_time":6.543818905},
{"learn":[2.668725082],"iteration":349,"passed_time":3.517963351,"remaining_time":6.533360509},
{"learn":[2.659351548],"iteration":350,"passed_time":3.527527468,"remaining_time":6.522408339},
{"learn":[2.65661973],"iteration":351,"passed_time":3.536652099,"remaining_time":6.510655},
{"learn":[2.655477719],"iteration":352,"passed_time":3.544886167,"remaining_time":6.497284278},
{"learn":[2.65391879],"iteration":353,"passed_time":3.55353581,"remaining_time":6.484700941},
{"learn":[2.651953072],"iteration":354,"passed_time":3.562343649,"remaining_time":6.472427193},
{"learn":[2.645271261],"iteration":355,"passed_time":3.571089904,"remaining_time":6.460061512},
{"learn":[2.637681436],"iteration":356,"passed_time":3.579294483,"remaining_time":6.446740484},
{"learn":[2.635436942],"iteration":357,"passed_time":3.58828311,"remaining_time":6.434854069},
{"learn":[2.629559876],"iteration":358,"passed_time":3.601526731,"remaining_time":6.430581156},
{"learn":[2.627930295],"iteration":359,"passed_time":3.612055412,"remaining_time":6.421431844},
{"learn":[2.617733305],"iteration":360,"passed_time":3.622212838,"remaining_time":6.411617739},
{"learn":[2.607270196],"iteration":361,"passed_time":3.631709726,"remaining_time":6.400637584},
{"learn":[2.599462249],"iteration":362,"passed_time":3.640697939,"remaining_time":6.388772968},
{"learn":[2.588957374],"iteration":363,"passed_time":3.649670935,"remaining_time":6.376897567},
{"learn":[2.581479113],"iteration":364,"passed_time":3.659726999,"remaining_time":6.366922313},
{"learn":[2.573553584],"iteration":365,"passed_time":3.669119244,"remaining_time":6.355796724},
{"learn":[2.564820658],"iteration":366,"passed_time":3.677597373,"remaining_time":6.343103916},
{"learn":[2.55662838],"iteration":367,"passed_time":3.687561671,"remaining_time":6.332986348},
{"learn":[2.549226582],"iteration":368,"passed_time":3.696638241,"remaining_time":6.321351572},
{"learn":[2.547828618],"iteration":369,"passed_time":3.704858798,"remaining_time":6.308273088},
{"learn":[2.537170953],"iteration":370,"passed_time":3.712978664,"remaining_time":6.295050079},
{"learn":[2.530862754],"iteration":371,"passed_time":3.721545494,"remaining_time":6.28260906},
{"learn":[2.52611842],"iteration":372,"passed_time":3.729774222,"remaining_time":6.269620475},
{"learn":[2.515863867],"iteration":373,"passed_time":3.73817197,"remaining_time":6.256940249},
{"learn":[2.506969589],"iteration":374,"passed_time":3.746458,"remaining_time":6.244096667},
{"learn":[2.504145363],"iteration":375,"passed_time":3.754802275,"remaining_time":6.231373989},
{"learn":[2.502857737],"iteration":376,"passed_time":3.763203452,"remaining_time":6.21876857},
{"learn":[2.496572523],"iteration":377,"passed_time":3.771701581,"remaining_time":6.206344929},
{"learn":[2.488260576],"iteration":378,"passed_time":3.779881257,"remaining_time":6.193420212},
{"learn":[2.479385374],"iteration":379,"passed_time":3.788173102,"remaining_time":6.180703482},
{"learn":[2.473133583],"iteration":380,"passed_time":3.799083524,"remaining_time":6.172264308},
{"learn":[2.466198698],"iteration":381,"passed_time":3.808666396,"remaining_time":6.161664484},
{"learn":[2.457123273],"iteration":382,"passed_time":3.817163215,"remaining_time":6.149320374},
{"learn":[2.455679709],"iteration":383,"passed_time":3.826634745,"remaining_time":6.138559904},
{"learn":[2.448389956],"iteration":384,"passed_time":3.836333938,"remaining_time":6.128169797},
{"learn":[2.440130144],"iteration":385,"passed_time":3.844972517,"remaining_time":6.11609618},
{"learn":[2.433778383],"iteration":386,"passed_time":3.853583411,"remaining_time":6.103996463},
{"learn":[2.425184835],"iteration":387,"passed_time":3.862969121,"remaining_time":6.093136861},
{"learn":[2.418425503],"iteration":388,"passed_time":3.87240264,"remaining_time":6.08235993},
{"learn":[2.415967434],"iteration":389,"passed_time":3.880842835,"remaining_time":6.070036228},
{"learn":[2.407358074],"iteration":390,"passed_time":3.890579686,"remaining_time":6.059751991},
{"learn":[2.39661948],"iteration":391,"passed_time":3.899283889,"remaining_time":6.04786889},
{"learn":[2.388938319],"iteration":392,"passed_time":3.907515631,"remaining_time":6.035272234},
{"learn":[2.387616576],"iteration":393,"passed_time":3.915564174,"remaining_time":6.022415963},
{"learn":[2.385469156],"iteration":394,"passed_time":3.923872315,"remaining_time":6.009981647},
{"learn":[2.37682365],"iteration":395,"passed_time":3.932181043,"remaining_time":5.997569066},
{"learn":[2.375899189],"iteration":396,"passed_time":3.940357452,"remaining_time":5.98497618},
{"learn":[2.368408734],"iteration":397,"passed_time":3.948457216,"remaining_time":5.972289558},
{"learn":[2.361277604],"iteration":398,"passed_time":3.956718234,"remaining_time":5.959868819},
{"learn":[2.353318545],"iteration":399,"passed_time":3.965581753,"remaining_time":5.948372629},
{"learn":[2.342384055],"iteration":400,"passed_time":3.973924328,"remaining_time":5.936111402},
{"learn":[2.341285064],"iteration":401,"passed_time":3.982005756,"remaining_time":5.9234812},
{"learn":[2.329763021],"iteration":402,"passed_time":3.99016417,"remaining_time":5.910987616},
{"learn":[2.32312918],"iteration":403,"passed_time":3.999142298,"remaining_time":5.899724777},
{"learn":[2.312989091],"iteration":404,"passed_time":4.00843211,"remaining_time":5.888931124},
{"learn":[2.311957182],"iteration":405,"passed_time":4.018107859,"remaining_time":5.878709528},
{"learn":[2.305690236],"iteration":406,"passed_time":4.027627679,"remaining_time":5.868263424},
{"learn":[2.296908232],"iteration":407,"passed_time":4.036654216,"remaining_time":5.857106117},
{"learn":[2.288268363],"iteration":408,"passed_time":4.04559585,"remaining_time":5.845836546},
{"learn":[2.279838684],"iteration":409,"passed_time":4.055324772,"remaining_time":5.835711257},
{"learn":[2.270654598],"iteration":410,"passed_time":4.063847836,"remaining_time":5.823859795},
{"learn":[2.264215378],"iteration":411,"passed_time":4.072649908,"remaining_time":5.812422684},
{"learn":[2.255779305],"iteration":412,"passed_time":4.082196065,"remaining_time":5.802055908},
{"learn":[2.243404941],"iteration":413,"passed_time":4.091566393,"remaining_time":5.791444217},
{"learn":[2.234819625],"iteration":414,"passed_time":4.100485348,"remaining_time":5.780202237},
{"learn":[2.228161731],"iteration":415,"passed_time":4.108674905,"remaining_time":5.767947463},
{"learn":[2.219753203],"iteration":416,"passed_time":4.117139247,"remaining_time":5.756096358},
{"learn":[2.218759777],"iteration":417,"passed_time":4.125409419,"remaining_time":5.743991105},
{"learn":[2.210995294],"iteration":418,"passed_time":4.133726199,"remaining_time":5.731968787},
{"learn":[2.203379756],"iteration":419,"passed_time":4.141723723,"remaining_time":5.719523237},
{"learn":[2.198568385],"iteration":420,"passed_time":4.150084332,"remaining_time":5.707598167},
{"learn":[2.19762475],"iteration":421,"passed_time":4.158271538,"remaining_time":5.695452486},
{"learn":[2.186562524],"iteration":422,"passed_time":4.166758538,"remaining_time":5.683734459},
{"learn":[2.178720483],"iteration":423,"passed_time":4.175411901,"remaining_time":5.672257676},
{"learn":[2.16726419],"iteration":424,"passed_time":4.185330042,"remaining_time":5.66250535},
{"learn":[2.166235737],"iteration":425,"passed_time":4.194397839,"remaining_time":5.651606478},
{"learn":[2.158789862],"iteration":426,"passed_time":4.203612001,"remaining_time":5.640912592},
{"learn":[2.152024496],"iteration":427,"passed_time":4.213388504,"remaining_time":5.630977159},
{"learn":[2.142625496],"iteration":428,"passed_time":4.223434305,"remaining_time":5.621400905},
{"learn":[2.137056777],"iteration":429,"passed_time":4.234012924,"remaining_time":5.61252876},
{"learn":[2.12954201],"iteration":430,"passed_time":4.243918619,"remaining_time":5.602760311},
{"learn":[2.120680436],"iteration":431,"passed_time":4.254030503,"remaining_time":5.593262328},
{"learn":[2.110002573],"iteration":432,"passed_time":4.265559392,"remaining_time":5.585617032},
{"learn":[2.102202765],"iteration":433,"passed_time":4.276490142,"remaining_time":5.57717378},
{"learn":[2.101145209],"iteration":434,"passed_time":4.287090184,"remaining_time":5.56828955},
{"learn":[2.094040327],"iteration":435,"passed_time":4.299388858,"remaining_time":5.561594762},
{"learn":[2.086634306],"iteration":436,"passed_time":4.308474108,"remaining_time":5.550734377},
{"learn":[2.077174715],"iteration":437,"passed_time":4.318661275,"remaining_time":5.541295973},
{"learn":[2.067691614],"iteration":438,"passed_time":4.328849515,"remaining_time":5.53185553},
{"learn":[2.064092143],"iteration":439,"passed_time":4.338997575,"remaining_time":5.52236055},
{"learn":[2.055383928],"iteration":440,"passed_time":4.348050615,"remaining_time":5.511474589},
{"learn":[2.050666327],"iteration":441,"passed_time":4.357598069,"remaining_time":5.501221092},
{"learn":[2.049808318],"iteration":442,"passed_time":4.367743565,"remaining_time":5.491722722},
{"learn":[2.041543311],"iteration":443,"passed_time":4.377326721,"remaining_time":5.481517245},
{"learn":[2.03628738],"iteration":444,"passed_time":4.386843888,"remaining_time":5.471232265},
{"learn":[2.035041878],"iteration":445,"passed_time":4.397372244,"remaining_time":5.462206778},
{"learn":[2.027168282],"iteration":446,"passed_time":4.406414371,"remaining_time":5.4513359},
{"learn":[2.019694988],"iteration":447,"passed_time":4.417833565,"remaining_time":5.443402072},
{"learn":[2.012172593],"iteration":448,"passed_time":4.429215262,"remaining_time":5.435406703},
{"learn":[2.010769219],"iteration":449,"passed_time":4.439097687,"remaining_time":5.42556384},
{"learn":[2.001909027],"iteration":450,"passed_time":4.44862391,"remaining_time":5.415287199},
{"learn":[1.998361015],"iteration":451,"passed_time":4.460135352,"remaining_time":5.407420737},
{"learn":[1.995630541],"iteration":452,"passed_time":4.470093037,"remaining_time":5.397662011},
{"learn":[1.991428151],"iteration":453,"passed_time":4.47934817,"remaining_time":5.38705749},
{"learn":[1.983756634],"iteration":454,"passed_time":4.488625381,"remaining_time":5.376485346},
{"learn":[1.97663267],"iteration":455,"passed_time":4.498032228,"remaining_time":5.366073535},
{"learn":[1.970507817],"iteration":456,"passed_time":4.508178561,"remaining_time":5.356544767},
{"learn":[1.966718126],"iteration":457,"passed_time":4.522344711,"remaining_time":5.351770379},
{"learn":[1.959497226],"iteration":458,"passed_time":4.531595685,"remaining_time":5.341161798},
{"learn":[1.953423035],"iteration":459,"passed_time":4.540005886,"remaining_time":5.329572127},
{"learn":[1.944627059],"iteration":460,"passed_time":4.548820953,"remaining_time":5.318469617},
{"learn":[1.937238658],"iteration":461,"passed_time":4.558604209,"remaining_time":5.308504469},
{"learn":[1.936102744],"iteration":462,"passed_time":4.568255353,"remaining_time":5.298386878},
{"learn":[1.926429051],"iteration":463,"passed_time":4.578314532,"remaining_time":5.288742649},
{"learn":[1.918656563],"iteration":464,"passed_time":4.587319264,"remaining_time":5.277883454},
{"learn":[1.90983341],"iteration":465,"passed_time":4.596886497,"remaining_time":5.267676802},
{"learn":[1.902137482],"iteration":466,"passed_time":4.605888097,"remaining_time":5.256827314},
{"learn":[1.897347365],"iteration":467,"passed_time":4.615883577,"remaining_time":5.24711552},
{"learn":[1.891112993],"iteration":468,"passed_time":4.625701142,"remaining_time":5.23720108},
{"learn":[1.884656072],"iteration":469,"passed_time":4.636624028,"remaining_time":5.228533478},
{"learn":[1.880810888],"iteration":470,"passed_time":4.647031683,"remaining_time":5.219277623},
{"learn":[1.879194289],"iteration":471,"passed_time":4.657070433,"remaining_time":5.209604213},
{"learn":[1.871149657],"iteration":472,"passed_time":4.666481612,"remaining_time":5.199230041},
{"learn":[1.863594065],"iteration":473,"passed_time":4.675847709,"remaining_time":5.188809904},
{"learn":[1.858623008],"iteration":474,"passed_time":4.685839667,"remaining_time":5.179085947},
{"learn":[1.853685414],"iteration":475,"passed_time":4.69628459,"remaining_time":5.169859506},
{"learn":[1.846578089],"iteration":476,"passed_time":4.706104433,"remaining_time":5.159942596},
{"learn":[1.841523262],"iteration":477,"passed_time":4.715795012,"remaining_time":5.14988493},
{"learn":[1.834173623],"iteration":478,"passed_time":4.726128207,"remaining_time":5.140527757},
{"learn":[1.829373118],"iteration":479,"passed_time":4.73582499,"remaining_time":5.130477073},
{"learn":[1.824201488],"iteration":480,"passed_time":4.745006318,"remaining_time":5.119871682},
{"learn":[1.818096173],"iteration":481,"passed_time":4.75460025,"remaining_time":5.109715622},
{"learn":[1.815095731],"iteration":482,"passed_time":4.763286042,"remaining_time":5.098589821},
{"learn":[1.814394884],"iteration":483,"passed_time":4.772585133,"remaining_time":5.088127952},
{"learn":[1.80559767],"iteration":484,"passed_time":4.781564674,"remaining_time":5.077331561},
{"learn":[1.801818626],"iteration":485,"passed_time":4.790372226,"remaining_time":5.066360749},
{"learn":[1.795370401],"iteration":486,"passed_time":4.799099729,"remaining_time":5.055314499},
{"learn":[1.793820627],"iteration":487,"passed_time":4.808213555,"remaining_time":5.044683074},
{"learn":[1.789165002],"iteration":488,"passed_time":4.816518587,"remaining_time":5.033212674},
{"learn":[1.78117427],"iteration":489,"passed_time":4.824891142,"remaining_time":5.021825475},
{"learn":[1.778439947],"iteration":490,"passed_time":4.834387392,"remaining_time":5.011615443},
{"learn":[1.772200949],"iteration":491,"passed_time":4.844291957,"remaining_time":5.001829907},
{"learn":[1.76545271],"iteration":492,"passed_time":4.85362774,"remaining_time":4.991458954},
{"learn":[1.764205026],"iteration":493,"passed_time":4.86380481,"remaining_time":4.981953915},
{"learn":[1.756660802],"iteration":494,"passed_time":4.874029575,"remaining_time":4.972494819},
{"learn":[1.753552654],"iteration":495,"passed_time":4.884180052,"remaining_time":4.962957149},
{"learn":[1.752132772],"iteration":496,"passed_time":4.894911769,"remaining_time":4.954005271},
{"learn":[1.751497856],"iteration":497,"passed_time":4.904300894,"remaining_time":4.943692869},
{"learn":[1.74578415],"iteration":498,"passed_time":4.913869844,"remaining_time":4.933564713},
{"learn":[1.739428401],"iteration":499,"passed_time":4.923095531,"remaining_time":4.923095531},
{"learn":[1.734490127],"iteration":500,"passed_time":4.932497652,"remaining_time":4.912807043},
{"learn":[1.72812],"iteration":501,"passed_time":4.941943332,"remaining_time":4.902565297},
{"learn":[1.726579845],"iteration":502,"passed_time":4.951541825,"remaining_time":4.892477708},
{"learn":[1.721537477],"iteration":503,"passed_time":4.961161247,"remaining_time":4.882412656},
{"learn":[1.716478786],"iteration":504,"passed_time":4.969612006,"remaining_time":4.871203847},
{"learn":[1.71589146],"iteration":505,"passed_time":4.978636314,"remaining_time":4.860565888},
{"learn":[1.711078277],"iteration":506,"passed_time":4.987289936,"remaining_time":4.849573843},
{"learn":[1.703945222],"iteration":507,"passed_time":4.996062977,"remaining_time":4.838706662},
{"learn":[1.700809806],"iteration":508,"passed_time":5.005110669,"remaining_time":4.82811265},
{"learn":[1.699887387],"iteration":509,"passed_time":5.013983495,"remaining_time":4.817356691},
{"learn":[1.692972692],"iteration":510,"passed_time":5.022915398,"remaining_time":4.806664637},
{"learn":[1.685491439],"iteration":511,"passed_time":5.031702283,"remaining_time":4.795841238},
{"learn":[1.684574911],"iteration":512,"passed_time":5.042559946,"remaining_time":4.786991606},
{"learn":[1.678948976],"iteration":513,"passed_time":5.05396275,"remaining_time":4.778649604},
{"learn":[1.674376167],"iteration":514,"passed_time":5.063510279,"remaining_time":4.768548515},
{"learn":[1.672089159],"iteration":515,"passed_time":5.073731294,"remaining_time":4.759081292},
{"learn":[1.670311331],"iteration":516,"passed_time":5.083658274,"remaining_time":4.749336453},
{"learn":[1.669307427],"iteration":517,"passed_time":5.093940171,"remaining_time":4.739921163},
{"learn":[1.668193852],"iteration":518,"passed_time":5.103736531,"remaining_time":4.730052546},
{"learn":[1.661711975],"iteration":519,"passed_time":5.113285847,"remaining_time":4.719956166},
{"learn":[1.65840434],"iteration":520,"passed_time":5.123415353,"remaining_time":4.710395305},
{"learn":[1.654197038],"iteration":521,"passed_time":5.133463414,"remaining_time":4.700757686},
{"learn":[1.650224347],"iteration":522,"passed_time":5.14250709,"remaining_time":4.690202451},
{"learn":[1.648892804],"iteration":523,"passed_time":5.152214753,"remaining_time":4.680256149},
{"learn":[1.647933729],"iteration":524,"passed_time":5.160825826,"remaining_time":4.669318605},
{"learn":[1.640107844],"iteration":525,"passed_time":5.170869151,"remaining_time":4.659680566},
{"learn":[1.633275037],"iteration":526,"passed_time":5.180042151,"remaining_time":4.649259843},
{"learn":[1.632318768],"iteration":527,"passed_time":5.189409502,"remaining_time":4.639017585},
{"learn":[1.626802505],"iteration":528,"passed_time":5.199463031,"remaining_time":4.62938958},
{"learn":[1.622627143],"iteration":529,"passed_time":5.208258856,"remaining_time":4.618644646},
{"learn":[1.616568042],"iteration":530,"passed_time":5.220510527,"remaining_time":4.610959392},
{"learn":[1.610799883],"iteration":531,"passed_time":5.229926637,"remaining_time":4.60076253},
{"learn":[1.609782737],"iteration":532,"passed_time":5.239455005,"remaining_time":4.590666956},
{"learn":[1.606451754],"iteration":533,"passed_time":5.259595752,"remaining_time":4.589834495},
{"learn":[1.602330791],"iteration":534,"passed_time":5.270842055,"remaining_time":4.58119917},
{"learn":[1.597492003],"iteration":535,"passed_time":5.281049544,"remaining_time":4.571654829},
{"learn":[1.592494195],"iteration":536,"passed_time":5.292177928,"remaining_time":4.562902013},
{"learn":[1.587617802],"iteration":537,"passed_time":5.302601922,"remaining_time":4.55353548},
{"learn":[1.580511735],"iteration":538,"passed_time":5.31267443,"remaining_time":4.543864401},
{"learn":[1.575537658],"iteration":539,"passed_time":5.322866158,"remaining_time":4.534293394},
{"learn":[1.574967706],"iteration":540,"passed_time":5.333173415,"remaining_time":4.52481811},
{"learn":[1.572651011],"iteration":541,"passed_time":5.344355492,"remaining_time":4.516078995},
{"learn":[1.567204418],"iteration":542,"passed_time":5.35527118,"remaining_time":4.507106684},
{"learn":[1.561617813],"iteration":543,"passed_time":5.36460771,"remaining_time":4.496803522},
{"learn":[1.555681991],"iteration":544,"passed_time":5.374260121,"remaining_time":4.486767624},
{"learn":[1.549549059],"iteration":545,"passed_time":5.383668697,"remaining_time":4.476530381},
{"learn":[1.545735541],"iteration":546,"passed_time":5.3927801,"remaining_time":4.466050065},
{"learn":[1.540036663],"iteration":547,"passed_time":5.402088128,"remaining_time":4.455736923},
{"learn":[1.535003443],"iteration":548,"passed_time":5.411521219,"remaining_time":4.445530182},
{"learn":[1.534196047],"iteration":549,"passed_time":5.4207134,"remaining_time":4.435129145},
{"learn":[1.527749909],"iteration":550,"passed_time":5.430236565,"remaining_time":4.42500221},
{"learn":[1.522036743],"iteration":551,"passed_time":5.439959709,"remaining_time":4.415039764},
{"learn":[1.520136692],"iteration":552,"passed_time":5.450433335,"remaining_time":4.405684811},
{"learn":[1.5191407],"iteration":553,"passed_time":5.45957658,"remaining_time":4.395254792},
{"learn":[1.51850039],"iteration":554,"passed_time":5.470343557,"remaining_time":4.386131321},
{"learn":[1.512342307],"iteration":555,"passed_time":5.480043608,"remaining_time":4.376149932},
{"learn":[1.508995206],"iteration":556,"passed_time":5.489576679,"remaining_time":4.366036748},
{"learn":[1.503436184],"iteration":557,"passed_time":5.500058234,"remaining_time":4.356676953},
{"learn":[1.498837798],"iteration":558,"passed_time":5.511484907,"remaining_time":4.348058755},
{"learn":[1.493326331],"iteration":559,"passed_time":5.522685672,"remaining_time":4.339253028},
{"learn":[1.488943152],"iteration":560,"passed_time":5.533021296,"remaining_time":4.329761763},
{"learn":[1.487525461],"iteration":561,"passed_time":5.542979966,"remaining_time":4.31997371},
{"learn":[1.483542164],"iteration":562,"passed_time":5.553386215,"remaining_time":4.310532462},
{"learn":[1.479195284],"iteration":563,"passed_time":5.563837334,"remaining_time":4.301122478},
{"learn":[1.472709188],"iteration":564,"passed_time":5.574294934,"remaining_time":4.291713798},
{"learn":[1.466779726],"iteration":565,"passed_time":5.583924736,"remaining_time":4.28166667},
{"learn":[1.462304335],"iteration":566,"passed_time":5.594145139,"remaining_time":4.272072037},
{"learn":[1.460172633],"iteration":567,"passed_time":5.604325759,"remaining_time":4.262444943},
{"learn":[1.458793208],"iteration":568,"passed_time":5.613605114,"remaining_time":4.252133223},
{"learn":[1.454375305],"iteration":569,"passed_time":5.623419364,"remaining_time":4.242228643},
{"learn":[1.448924579],"iteration":570,"passed_time":5.632502514,"remaining_time":4.231775094},
{"learn":[1.441149806],"iteration":571,"passed_time":5.642234396,"remaining_time":4.22181175},
{"learn":[1.437096228],"iteration":572,"passed_time":5.651591853,"remaining_time":4.211570194},
{"learn":[1.43603865],"iteration":573,"passed_time":5.661884399,"remaining_time":4.202025704},
{"learn":[1.430283338],"iteration":574,"passed_time":5.673084463,"remaining_time":4.193149386},
{"learn":[1.42567766],"iteration":575,"passed_time":5.684890726,"remaining_time":4.184711229},
{"learn":[1.424226382],"iteration":576,"passed_time":5.695542221,"remaining_time":4.175414835},
{"learn":[1.422986477],"iteration":577,"passed_time":5.705374123,"remaining_time":4.165515363},
{"learn":[1.42187696],"iteration":578,"passed_time":5.715909108,"remaining_time":4.156127348},
{"learn":[1.417618187],"iteration":579,"passed_time":5.726749616,"remaining_time":4.146956618},
{"learn":[1.413858812],"iteration":580,"passed_time":5.737511302,"remaining_time":4.137723297},
{"learn":[1.40903507],"iteration":581,"passed_time":5.747888495,"remaining_time":4.128208575},
{"learn":[1.40415064],"iteration":582,"passed_time":5.758515877,"remaining_time":4.118869847},
{"learn":[1.398822285],"iteration":583,"passed_time":5.769011948,"remaining_time":4.109433169},
{"learn":[1.393820867],"iteration":584,"passed_time":5.778744715,"remaining_time":4.099451379},
{"learn":[1.390728044],"iteration":585,"passed_time":5.788375254,"remaining_time":4.089398217},
{"learn":[1.383838489],"iteration":586,"passed_time":5.798337969,"remaining_time":4.079580206},
{"learn":[1.378558052],"iteration":587,"passed_time":5.80890821,"remaining_time":4.070187385},
{"learn":[1.378067653],"iteration":588,"passed_time":5.818794766,"remaining_time":4.060313495},
{"learn":[1.37376596],"iteration":589,"passed_time":5.828398164,"remaining_time":4.050242792},
{"learn":[1.370257975],"iteration":590,"passed_time":5.838560754,"remaining_time":4.040560657},
{"learn":[1.365309595],"iteration":591,"passed_time":5.848966291,"remaining_time":4.031044336},
{"learn":[1.359710818],"iteration":592,"passed_time":5.858419029,"remaining_time":4.020871071},
{"learn":[1.359114266],"iteration":593,"passed_time":5.869026356,"remaining_time":4.011489395},
{"learn":[1.355360324],"iteration":594,"passed_time":5.880850998,"remaining_time":4.002932192},
{"learn":[1.353881416],"iteration":595,"passed_time":5.892509649,"remaining_time":3.994251507},
{"learn":[1.34797375],"iteration":596,"passed_time":5.904631365,"remaining_time":3.985873434},
{"learn":[1.343823163],"iteration":597,"passed_time":5.916623424,"remaining_time":3.97739568},
{"learn":[1.34147905],"iteration":598,"passed_time":5.928705238,"remaining_time":3.968966278},
{"learn":[1.339677613],"iteration":599,"passed_time":5.943282052,"remaining_time":3.962188035},
{"learn":[1.335685262],"iteration":600,"passed_time":5.955886058,"remaining_time":3.954074105},
{"learn":[1.332355017],"iteration":601,"passed_time":5.967231753,"remaining_time":3.945113352},
{"learn":[1.331865045],"iteration":602,"passed_time":5.977765684,"remaining_time":3.935610243},
{"learn":[1.328937941],"iteration":603,"passed_time":5.988773018,"remaining_time":3.926414098},
{"learn":[1.323245323],"iteration":604,"passed_time":6.000403168,"remaining_time":3.917618598},
{"learn":[1.317308954],"iteration":605,"passed_time":6.010758111,"remaining_time":3.907984646},
{"learn":[1.316705161],"iteration":606,"passed_time":6.021136987,"remaining_time":3.898363815},
{"learn":[1.314505884],"iteration":607,"passed_time":6.033211405,"remaining_time":3.889833669},
{"learn":[1.313569563],"iteration":608,"passed_time":6.044626796,"remaining_time":3.880868764},
{"learn":[1.312903388],"iteration":609,"passed_time":6.056397583,"remaining_time":3.872123045},
{"learn":[1.307436027],"iteration":610,"passed_time":6.068304771,"remaining_time":3.863454265},
{"learn":[1.305350524],"iteration":611,"passed_time":6.079778563,"remaining_time":3.854500135},
{"learn":[1.304501231],"iteration":612,"passed_time":6.092311993,"remaining_time":3.846206756},
{"learn":[1.299749807],"iteration":613,"passed_time":6.105566764,"remaining_time":3.838353047},
{"learn":[1.29558584],"iteration":614,"passed_time":6.117683731,"remaining_time":3.82976949},
{"learn":[1.289543611],"iteration":615,"passed_time":6.129602398,"remaining_time":3.821050845},
{"learn":[1.283651332],"iteration":616,"passed_time":6.143275345,"remaining_time":3.81341079},
{"learn":[1.279885941],"iteration":617,"passed_time":6.157981148,"remaining_time":3.806389641},
{"learn":[1.279444859],"iteration":618,"passed_time":6.171238595,"remaining_time":3.798452188},
{"learn":[1.275359254],"iteration":619,"passed_time":6.183012883,"remaining_time":3.789588541},
{"learn":[1.274346157],"iteration":620,"passed_time":6.194065177,"remaining_time":3.780274882},
{"learn":[1.269732964],"iteration":621,"passed_time":6.206074296,"remaining_time":3.771537113},
{"learn":[1.269224832],"iteration":622,"passed_time":6.217787257,"remaining_time":3.762609624},
{"learn":[1.265482922],"iteration":623,"passed_time":6.229552385,"remaining_time":3.753704642},
{"learn":[1.260824092],"iteration":624,"passed_time":6.241025246,"remaining_time":3.744615148},
{"learn":[1.258951936],"iteration":625,"passed_time":6.252387056,"remaining_time":3.735451691},
{"learn":[1.258467071],"iteration":626,"passed_time":6.262771221,"remaining_time":3.725699626},
{"learn":[1.253299732],"iteration":627,"passed_time":6.272825527,"remaining_time":3.715750153},
{"learn":[1.248758668],"iteration":628,"passed_time":6.283098811,"remaining_time":3.705929505},
{"learn":[1.248082645],"iteration":629,"passed_time":6.294968377,"remaining_time":3.69704492},
{"learn":[1.24590291],"iteration":630,"passed_time":6.305806681,"remaining_time":3.687547806},
{"learn":[1.242394587],"iteration":631,"passed_time":6.316834454,"remaining_time":3.678156771},
{"learn":[1.241692643],"iteration":632,"passed_time":6.328944669,"remaining_time":3.669388141},
{"learn":[1.236501617],"iteration":633,"passed_time":6.340042172,"remaining_time":3.660024345},
{"learn":[1.234953062],"iteration":634,"passed_time":6.350418133,"remaining_time":3.650240344},
{"learn":[1.229430476],"iteration":635,"passed_time":6.361868162,"remaining_time":3.6410692},
{"learn":[1.225996348],"iteration":636,"passed_time":6.372559589,"remaining_time":3.631458604},
{"learn":[1.222670061],"iteration":637,"passed_time":6.383239975,"remaining_time":3.621838356},
{"learn":[1.222194756],"iteration":638,"passed_time":6.393585034,"remaining_time":3.612025348},
{"learn":[1.221358799],"iteration":639,"passed_time":6.404292337,"remaining_time":3.602414439},
{"learn":[1.216914174],"iteration":640,"passed_time":6.413552691,"remaining_time":3.591989729},
{"learn":[1.212756914],"iteration":641,"passed_time":6.424250002,"remaining_time":3.582369939},
{"learn":[1.207410548],"iteration":642,"passed_time":6.433776222,"remaining_time":3.572096596},
{"learn":[1.203608268],"iteration":643,"passed_time":6.443986563,"remaining_time":3.562203752},
{"learn":[1.20013391],"iteration":644,"passed_time":6.45451244,"remaining_time":3.552483591},
{"learn":[1.195343572],"iteration":645,"passed_time":6.465674279,"remaining_time":3.543109435},
{"learn":[1.194678571],"iteration":646,"passed_time":6.476386796,"remaining_time":3.533484604},
{"learn":[1.191448014],"iteration":647,"passed_time":6.485949998,"remaining_time":3.523232098},
{"learn":[1.187193198],"iteration":648,"passed_time":6.498270318,"remaining_time":3.514472853},
{"learn":[1.184161167],"iteration":649,"passed_time":6.509331269,"remaining_time":3.505024529},
{"learn":[1.18008501],"iteration":650,"passed_time":6.520568166,"remaining_time":3.495665576},
{"learn":[1.174827123],"iteration":651,"passed_time":6.532231915,"remaining_time":3.486528691},
{"learn":[1.17212514],"iteration":652,"passed_time":6.543129904,"remaining_time":3.476977147},
{"learn":[1.168186041],"iteration":653,"passed_time":6.55417008,"remaining_time":3.467496709},
{"learn":[1.164408795],"iteration":654,"passed_time":6.566188058,"remaining_time":3.458526534},
{"learn":[1.163709522],"iteration":655,"passed_time":6.577617645,"remaining_time":3.449238521},
{"learn":[1.160979907],"iteration":656,"passed_time":6.588516878,"remaining_time":3.439667107},
{"learn":[1.160528229],"iteration":657,"passed_time":6.598447649,"remaining_time":3.429588292},
{"learn":[1.156844254],"iteration":658,"passed_time":6.609382311,"remaining_time":3.42002939},
{"learn":[1.151345686],"iteration":659,"passed_time":6.619397574,"remaining_time":3.40999269},
{"learn":[1.148782421],"iteration":660,"passed_time":6.629751965,"remaining_time":3.400129979},
{"learn":[1.144210778],"iteration":661,"passed_time":6.639482002,"remaining_time":3.389947004},
{"learn":[1.140223004],"iteration":662,"passed_time":6.648774374,"remaining_time":3.379542932},
{"learn":[1.137049422],"iteration":663,"passed_time":6.65870235,"remaining_time":3.36946384},
{"learn":[1.133425321],"iteration":664,"passed_time":6.66845244,"remaining_time":3.35929559},
{"learn":[1.132132113],"iteration":665,"passed_time":6.678596309,"remaining_time":3.349326077},
{"learn":[1.130547341],"iteration":666,"passed_time":6.687773277,"remaining_time":3.338873315},
{"learn":[1.128066204],"iteration":667,"passed_time":6.701300035,"remaining_time":3.330586245},
{"learn":[1.126265445],"iteration":668,"passed_time":6.713442743,"remaining_time":3.321598726},
{"learn":[1.124857568],"iteration":669,"passed_time":6.723996722,"remaining_time":3.311819281},
{"learn":[1.121570908],"iteration":670,"passed_time":6.73519953,"remaining_time":3.302355656},
{"learn":[1.117646712],"iteration":671,"passed_time":6.745946521,"remaining_time":3.292664373},
{"learn":[1.115246945],"iteration":672,"passed_time":6.756959926,"remaining_time":3.283099399},
{"learn":[1.11339021],"iteration":673,"passed_time":6.767314758,"remaining_time":3.273211589},
{"learn":[1.109825924],"iteration":674,"passed_time":6.777460158,"remaining_time":3.263221558},
{"learn":[1.109360631],"iteration":675,"passed_time":6.788697062,"remaining_time":3.253754213},
{"learn":[1.103861143],"iteration":676,"passed_time":6.799197266,"remaining_time":3.243930158},
{"learn":[1.100567723],"iteration":677,"passed_time":6.809503235,"remaining_time":3.234011861},
{"learn":[1.095920706],"iteration":678,"passed_time":6.819064069,"remaining_time":3.223740156},
{"learn":[1.095263587],"iteration":679,"passed_time":6.828718295,"remaining_time":3.213514492},
{"learn":[1.089901947],"iteration":680,"passed_time":6.838124956,"remaining_time":3.203174539},
{"learn":[1.086308928],"iteration":681,"passed_time":6.849025892,"remaining_time":3.193534067},
{"learn":[1.082221729],"iteration":682,"passed_time":6.859302815,"remaining_time":3.183600281},
{"learn":[1.078733918],"iteration":683,"passed_time":6.869952186,"remaining_time":3.17383756},
{"learn":[1.077788861],"iteration":684,"passed_time":6.879774156,"remaining_time":3.163691765},
{"learn":[1.077095991],"iteration":685,"passed_time":6.888902397,"remaining_time":3.153229377},
{"learn":[1.073204891],"iteration":686,"passed_time":6.899163056,"remaining_time":3.143286807},
{"learn":[1.0727443],"iteration":687,"passed_time":6.909122072,"remaining_time":3.133206521},
{"learn":[1.06801157],"iteration":688,"passed_time":6.919422916,"remaining_time":3.123280881},
{"learn":[1.065132586],"iteration":689,"passed_time":6.930897889,"remaining_time":3.11388166},
{"learn":[1.064776893],"iteration":690,"passed_time":6.942244414,"remaining_time":3.104418993},
{"learn":[1.062521497],"iteration":691,"passed_time":6.953608633,"remaining_time":3.094958756},
{"learn":[1.059287325],"iteration":692,"passed_time":6.965607704,"remaining_time":3.085774264},
{"learn":[1.057421149],"iteration":693,"passed_time":6.977050795,"remaining_time":3.076336518},
{"learn":[1.056818087],"iteration":694,"passed_time":6.988002348,"remaining_time":3.066677289},
{"learn":[1.05358886],"iteration":695,"passed_time":6.998584286,"remaining_time":3.056852906},
{"learn":[1.049942001],"iteration":696,"passed_time":7.007886414,"remaining_time":3.046469991},
{"learn":[1.045971453],"iteration":697,"passed_time":7.017178869,"remaining_time":3.036085986},
{"learn":[1.045583908],"iteration":698,"passed_time":7.026568793,"remaining_time":3.025747077},
{"learn":[1.043901947],"iteration":699,"passed_time":7.036358726,"remaining_time":3.015582311},
{"learn":[1.041664632],"iteration":700,"passed_time":7.046660501,"remaining_time":3.005636933},
{"learn":[1.039010056],"iteration":701,"passed_time":7.056103476,"remaining_time":2.995325977},
{"learn":[1.035215095],"iteration":702,"passed_time":7.065385897,"remaining_time":2.984949661},
{"learn":[1.031914205],"iteration":703,"passed_time":7.075117649,"remaining_time":2.974765375},
{"learn":[1.029124787],"iteration":704,"passed_time":7.084454386,"remaining_time":2.964417084},
{"learn":[1.025002873],"iteration":705,"passed_time":7.093851393,"remaining_time":2.954096756},
{"learn":[1.020223868],"iteration":706,"passed_time":7.104723094,"remaining_time":2.944390193},
{"learn":[1.019044314],"iteration":707,"passed_time":7.114615319,"remaining_time":2.934276374},
{"learn":[1.015429678],"iteration":708,"passed_time":7.124462842,"remaining_time":2.924144834},
{"learn":[1.011796352],"iteration":709,"passed_time":7.134505835,"remaining_time":2.914093932},
{"learn":[1.00927433],"iteration":710,"passed_time":7.145118413,"remaining_time":2.904274573},
{"learn":[1.005350048],"iteration":711,"passed_time":7.15579265,"remaining_time":2.894477926},
{"learn":[1.000882044],"iteration":712,"passed_time":7.166775293,"remaining_time":2.884802958},
{"learn":[0.9970859303],"iteration":713,"passed_time":7.176560075,"remaining_time":2.874644512},
{"learn":[0.9937213729],"iteration":714,"passed_time":7.186256564,"remaining_time":2.864451917},
{"learn":[0.9904672048],"iteration":715,"passed_time":7.196434082,"remaining_time":2.854451507},
{"learn":[0.9900338322],"iteration":716,"passed_time":7.205697278,"remaining_time":2.84408972},
{"learn":[0.987353843],"iteration":717,"passed_time":7.215485113,"remaining_time":2.83393705},
{"learn":[0.9835790098],"iteration":718,"passed_time":7.225039463,"remaining_time":2.823694144},
{"learn":[0.9800970304],"iteration":719,"passed_time":7.234585902,"remaining_time":2.813450073},
{"learn":[0.9762999807],"iteration":720,"passed_time":7.244204008,"remaining_time":2.80323567},
{"learn":[0.9727473434],"iteration":721,"passed_time":7.254117364,"remaining_time":2.793136603},
{"learn":[0.9723033837],"iteration":722,"passed_time":7.264169925,"remaining_time":2.783091382},
{"learn":[0.9696736204],"iteration":723,"passed_time":7.275140487,"remaining_time":2.773396097},
{"learn":[0.9674633197],"iteration":724,"passed_time":7.2859318,"remaining_time":2.763629303},
{"learn":[0.9656664751],"iteration":725,"passed_time":7.295919452,"remaining_time":2.753556377},
{"learn":[0.9618232512],"iteration":726,"passed_time":7.309586492,"remaining_time":2.744865354},
{"learn":[0.9578821979],"iteration":727,"passed_time":7.320968423,"remaining_time":2.735306883},
{"learn":[0.9542721503],"iteration":728,"passed_time":7.33214696,"remaining_time":2.7256678},
{"learn":[0.9523498649],"iteration":729,"passed_time":7.343336956,"remaining_time":2.716028737},
{"learn":[0.9504843201],"iteration":730,"passed_time":7.354715538,"remaining_time":2.706454829},
{"learn":[0.948192058],"iteration":731,"passed_time":7.366435344,"remaining_time":2.697000918},
{"learn":[0.9442283143],"iteration":732,"passed_time":7.377054309,"remaining_time":2.687139837},
{"learn":[0.9415110228],"iteration":733,"passed_time":7.38753317,"remaining_time":2.677225917},
{"learn":[0.9398881116],"iteration":734,"passed_time":7.399046346,"remaining_time":2.667683376},
{"learn":[0.9373624303],"iteration":735,"passed_time":7.40900468,"remaining_time":2.657577766},
{"learn":[0.9365687074],"iteration":736,"passed_time":7.420291666,"remaining_time":2.647946687},
{"learn":[0.9340006535],"iteration":737,"passed_time":7.430538622,"remaining_time":2.637941896},
{"learn":[0.9299317232],"iteration":738,"passed_time":7.440554983,"remaining_time":2.627855008},
{"learn":[0.926313972],"iteration":739,"passed_time":7.450753797,"remaining_time":2.617832415},
{"learn":[0.9229257546],"iteration":740,"passed_time":7.461680262,"remaining_time":2.608063681},
{"learn":[0.9223709935],"iteration":741,"passed_time":7.472275559,"remaining_time":2.598176677},
{"learn":[0.9182440296],"iteration":742,"passed_time":7.483156886,"remaining_time":2.588386702},
{"learn":[0.9164381714],"iteration":743,"passed_time":7.493381915,"remaining_time":2.578367971},
{"learn":[0.9161420857],"iteration":744,"passed_time":7.503982953,"remaining_time":2.568477387},
{"learn":[0.912802844],"iteration":745,"passed_time":7.514767673,"remaining_time":2.558647438},
{"learn":[0.908708488],"iteration":746,"passed_time":7.525827008,"remaining_time":2.548907942},
{"learn":[0.9081338748],"iteration":747,"passed_time":7.537146021,"remaining_time":2.539252403},
{"learn":[0.9052799972],"iteration":748,"passed_time":7.549068325,"remaining_time":2.529794592},
{"learn":[0.9025648214],"iteration":749,"passed_time":7.560977797,"remaining_time":2.520325932},
{"learn":[0.9019649049],"iteration":750,"passed_time":7.572090879,"remaining_time":2.510586723},
{"learn":[0.9013689031],"iteration":751,"passed_time":7.583372696,"remaining_time":2.500899506},
{"learn":[0.898918551],"iteration":752,"passed_time":7.595044165,"remaining_time":2.491335868},
{"learn":[0.8949339001],"iteration":753,"passed_time":7.60685675,"remaining_time":2.48181268},
{"learn":[0.8933424547],"iteration":754,"passed_time":7.616730524,"remaining_time":2.471654276},
{"learn":[0.8907238328],"iteration":755,"passed_time":7.626855671,"remaining_time":2.461577756},
{"learn":[0.8879119424],"iteration":756,"passed_time":7.636638975,"remaining_time":2.451391375},
{"learn":[0.8852554988],"iteration":757,"passed_time":7.646603831,"remaining_time":2.44126402},
{"learn":[0.8818520242],"iteration":758,"passed_time":7.656156598,"remaining_time":2.431006245},
{"learn":[0.8816197207],"iteration":759,"passed_time":7.665791608,"remaining_time":2.420776297},
{"learn":[0.8782194074],"iteration":760,"passed_time":7.676083777,"remaining_time":2.4107543},
{"learn":[0.8749095185],"iteration":761,"passed_time":7.686060527,"remaining_time":2.400633078},
{"learn":[0.8727771353],"iteration":762,"passed_time":7.695582546,"remaining_time":2.390370987},
{"learn":[0.8706287593],"iteration":763,"passed_time":7.705699884,"remaining_time":2.380294729},
{"learn":[0.8676267625],"iteration":764,"passed_time":7.716767851,"remaining_time":2.370510386},
{"learn":[0.8652991116],"iteration":765,"passed_time":7.727231182,"remaining_time":2.360537985},
{"learn":[0.8627274262],"iteration":766,"passed_time":7.738148905,"remaining_time":2.35070234},
{"learn":[0.8589899233],"iteration":767,"passed_time":7.749438659,"remaining_time":2.340976262},
{"learn":[0.8577426638],"iteration":768,"passed_time":7.760805514,"remaining_time":2.331269277},
{"learn":[0.8573951347],"iteration":769,"passed_time":7.771488758,"remaining_time":2.321353785},
{"learn":[0.8548837595],"iteration":770,"passed_time":7.782294583,"remaining_time":2.31147271},
{"learn":[0.8529291993],"iteration":771,"passed_time":7.79409186,"remaining_time":2.301882052},
{"learn":[0.8525668964],"iteration":772,"passed_time":7.805387277,"remaining_time":2.292138308},
{"learn":[0.85203123],"iteration":773,"passed_time":7.816142243,"remaining_time":2.282232748},
{"learn":[0.8492752408],"iteration":774,"passed_time":7.827282456,"remaining_time":2.272436842},
{"learn":[0.8484572445],"iteration":775,"passed_time":7.837667349,"remaining_time":2.262419441},
{"learn":[0.848104779],"iteration":776,"passed_time":7.848018381,"remaining_time":2.252391376},
{"learn":[0.8472867301],"iteration":777,"passed_time":7.858579196,"remaining_time":2.242422341},
{"learn":[0.8448735305],"iteration":778,"passed_time":7.869204133,"remaining_time":2.232469979},
{"learn":[0.8419492435],"iteration":779,"passed_time":7.878789402,"remaining_time":2.222222652},
{"learn":[0.8384380251],"iteration":780,"passed_time":7.888717788,"remaining_time":2.212073234},
{"learn":[0.8349513486],"iteration":781,"passed_time":7.898643705,"remaining_time":2.201923693},
{"learn":[0.8333657876],"iteration":782,"passed_time":7.908382549,"remaining_time":2.191722878},
{"learn":[0.8328402757],"iteration":783,"passed_time":7.921491898,"remaining_time":2.182451849},
{"learn":[0.8316113525],"iteration":784,"passed_time":7.932275287,"remaining_time":2.172533996},
{"learn":[0.8289273996],"iteration":785,"passed_time":7.944679979,"remaining_time":2.163055363},
{"learn":[0.8262968679],"iteration":786,"passed_time":7.961811913,"remaining_time":2.154848713},
{"learn":[0.824479935],"iteration":787,"passed_time":7.973120096,"remaining_time":2.145052615},
{"learn":[0.8222982904],"iteration":788,"passed_time":7.983880585,"remaining_time":2.135106215},
{"learn":[0.8217001703],"iteration":789,"passed_time":7.994286232,"remaining_time":2.125063429},
{"learn":[0.8211705685],"iteration":790,"passed_time":8.005312407,"remaining_time":2.115183683},
{"learn":[0.8207655509],"iteration":791,"passed_time":8.015523053,"remaining_time":2.105086862},
{"learn":[0.8172980289],"iteration":792,"passed_time":8.02552168,"remaining_time":2.094934411},
{"learn":[0.8162718082],"iteration":793,"passed_time":8.035526011,"remaining_time":2.084783827},
{"learn":[0.8151653738],"iteration":794,"passed_time":8.045251359,"remaining_time":2.074561671},
{"learn":[0.8147846402],"iteration":795,"passed_time":8.055196842,"remaining_time":2.064397181},
{"learn":[0.8122454888],"iteration":796,"passed_time":8.065336431,"remaining_time":2.05428268},
{"learn":[0.80994155],"iteration":797,"passed_time":8.075126576,"remaining_time":2.04407966},
{"learn":[0.8094527039],"iteration":798,"passed_time":8.085108988,"remaining_time":2.033926041},
{"learn":[0.8083421046],"iteration":799,"passed_time":8.095028494,"remaining_time":2.023757123},
{"learn":[0.8058120507],"iteration":800,"passed_time":8.104987471,"remaining_time":2.013598635},
{"learn":[0.8048404322],"iteration":801,"passed_time":8.115084717,"remaining_time":2.00347478},
{"learn":[0.8030526348],"iteration":802,"passed_time":8.125315153,"remaining_time":1.993383668},
{"learn":[0.8027127276],"iteration":803,"passed_time":8.135695679,"remaining_time":1.983328797},
{"learn":[0.7989433997],"iteration":804,"passed_time":8.146737582,"remaining_time":1.973433327},
{"learn":[0.7958376982],"iteration":805,"passed_time":8.1583008,"remaining_time":1.96366049},
{"learn":[0.7941805003],"iteration":806,"passed_time":8.169628454,"remaining_time":1.953826879},
{"learn":[0.7908240973],"iteration":807,"passed_time":8.181726906,"remaining_time":1.94417273},
{"learn":[0.7881990811],"iteration":808,"passed_time":8.19334781,"remaining_time":1.934399792},
{"learn":[0.7876638732],"iteration":809,"passed_time":8.204713194,"remaining_time":1.924562354},
{"learn":[0.7872667639],"iteration":810,"passed_time":8.215386554,"remaining_time":1.914559875},
{"learn":[0.7841533339],"iteration":811,"passed_time":8.225407092,"remaining_time":1.904404598},
{"learn":[0.7824873718],"iteration":812,"passed_time":8.235534072,"remaining_time":1.894274135},
{"learn":[0.7808109024],"iteration":813,"passed_time":8.245330232,"remaining_time":1.884068087},
{"learn":[0.7801783421],"iteration":814,"passed_time":8.255030588,"remaining_time":1.873841299},
{"learn":[0.7782431554],"iteration":815,"passed_time":8.264812854,"remaining_time":1.863634271},
{"learn":[0.7739888923],"iteration":816,"passed_time":8.274497853,"remaining_time":1.853406496},
{"learn":[0.7714367192],"iteration":817,"passed_time":8.283916575,"remaining_time":1.843120803},
{"learn":[0.7704380498],"iteration":818,"passed_time":8.293614778,"remaining_time":1.832898992},
{"learn":[0.7699619304],"iteration":819,"passed_time":8.30274631,"remaining_time":1.822554068},
{"learn":[0.7669836199],"iteration":820,"passed_time":8.312231296,"remaining_time":1.812289162},
{"learn":[0.7640973019],"iteration":821,"passed_time":8.321729391,"remaining_time":1.802028992},
{"learn":[0.7611179224],"iteration":822,"passed_time":8.333971477,"remaining_time":1.792360816},
{"learn":[0.7587236973],"iteration":823,"passed_time":8.344924875,"remaining_time":1.782411138},
{"learn":[0.7581244075],"iteration":824,"passed_time":8.355327777,"remaining_time":1.772342256},
{"learn":[0.7559447266],"iteration":825,"passed_time":8.366097016,"remaining_time":1.762349735},
{"learn":[0.7554587919],"iteration":826,"passed_time":8.377088262,"remaining_time":1.752401777},
{"learn":[0.7521803194],"iteration":827,"passed_time":8.389048636,"remaining_time":1.742652615},
{"learn":[0.7506964478],"iteration":828,"passed_time":8.399490659,"remaining_time":1.732584925},
{"learn":[0.748493049],"iteration":829,"passed_time":8.412232061,"remaining_time":1.72298729},
{"learn":[0.7459457903],"iteration":830,"passed_time":8.424368795,"remaining_time":1.713259117},
{"learn":[0.7455793243],"iteration":831,"passed_time":8.435554073,"remaining_time":1.703333034},
{"learn":[0.7435188644],"iteration":832,"passed_time":8.446191504,"remaining_time":1.693294095},
{"learn":[0.743082369],"iteration":833,"passed_time":8.456327175,"remaining_time":1.68315385},
{"learn":[0.7400052628],"iteration":834,"passed_time":8.467301042,"remaining_time":1.673179248},
{"learn":[0.7364124697],"iteration":835,"passed_time":8.477968879,"remaining_time":1.66314222},
{"learn":[0.7347935065],"iteration":836,"passed_time":8.488098847,"remaining_time":1.652998939},
{"learn":[0.734104777],"iteration":837,"passed_time":8.497771574,"remaining_time":1.642767297},
{"learn":[0.733168395],"iteration":838,"passed_time":8.508073003,"remaining_time":1.632657632},
{"learn":[0.7311816344],"iteration":839,"passed_time":8.517542909,"remaining_time":1.622389126},
{"learn":[0.7285186709],"iteration":840,"passed_time":8.528177933,"remaining_time":1.612342796},
{"learn":[0.7281885378],"iteration":841,"passed_time":8.538729888,"remaining_time":1.60227948},
{"learn":[0.7254703743],"iteration":842,"passed_time":8.549256975,"remaining_time":1.592210374},
{"learn":[0.7234474821],"iteration":843,"passed_time":8.560948194,"remaining_time":1.582355353},
{"learn":[0.7231966568],"iteration":844,"passed_time":8.572423661,"remaining_time":1.572456411},
{"learn":[0.7209602846],"iteration":845,"passed_time":8.583703243,"remaining_time":1.562518084},
{"learn":[0.7205821568],"iteration":846,"passed_time":8.594561845,"remaining_time":1.552500546},
{"learn":[0.7202356054],"iteration":847,"passed_time":8.605628276,"remaining_time":1.542518276},
{"learn":[0.718194302],"iteration":848,"passed_time":8.617702254,"remaining_time":1.532712651},
{"learn":[0.7157746252],"iteration":849,"passed_time":8.629337908,"remaining_time":1.522824337},
{"learn":[0.7137230094],"iteration":850,"passed_time":8.640688462,"remaining_time":1.512881999},
{"learn":[0.7125289233],"iteration":851,"passed_time":8.651798661,"remaining_time":1.502894603},
{"learn":[0.7096516389],"iteration":852,"passed_time":8.661299695,"remaining_time":1.492627263},
{"learn":[0.7092686832],"iteration":853,"passed_time":8.671930186,"remaining_time":1.482554809},
{"learn":[0.7074913612],"iteration":854,"passed_time":8.681615523,"remaining_time":1.472320761},
{"learn":[0.7064918039],"iteration":855,"passed_time":8.692089491,"remaining_time":1.462220662},
{"learn":[0.7039785639],"iteration":856,"passed_time":8.703320247,"remaining_time":1.452245969},
{"learn":[0.7012229678],"iteration":857,"passed_time":8.713691705,"remaining_time":1.442126133},
{"learn":[0.6998409953],"iteration":858,"passed_time":8.724014832,"remaining_time":1.431997778},
{"learn":[0.6971048965],"iteration":859,"passed_time":8.736750668,"remaining_time":1.422261737},
{"learn":[0.6936744283],"iteration":860,"passed_time":8.748024858,"remaining_time":1.412282759},
{"learn":[0.6911356387],"iteration":861,"passed_time":8.75885423,"remaining_time":1.402229564},
{"learn":[0.6897335102],"iteration":862,"passed_time":8.769703509,"remaining_time":1.39217773},
{"learn":[0.687334515],"iteration":863,"passed_time":8.780475683,"remaining_time":1.382111913},
{"learn":[0.6840829347],"iteration":864,"passed_time":8.79216178,"remaining_time":1.372187099},
{"learn":[0.6822405466],"iteration":865,"passed_time":8.803484635,"remaining_time":1.36220201},
{"learn":[0.6801515092],"iteration":866,"passed_time":8.815044815,"remaining_time":1.352250243},
{"learn":[0.6785763377],"iteration":867,"passed_time":8.826723189,"remaining_time":1.342312743},
{"learn":[0.6771043308],"iteration":868,"passed_time":8.837611341,"remaining_time":1.332252112},
{"learn":[0.674618762],"iteration":869,"passed_time":8.84910422,"remaining_time":1.322279941},
{"learn":[0.6723395238],"iteration":870,"passed_time":8.859011472,"remaining_time":1.312069437},
{"learn":[0.6711417213],"iteration":871,"passed_time":8.869520805,"remaining_time":1.301948008},
{"learn":[0.6690412284],"iteration":872,"passed_time":8.879244598,"remaining_time":1.291711413},
{"learn":[0.6687523726],"iteration":873,"passed_time":8.88916372,"remaining_time":1.281504152},
{"learn":[0.668373705],"iteration":874,"passed_time":8.898524944,"remaining_time":1.271217849},
{"learn":[0.6667334823],"iteration":875,"passed_time":8.909574297,"remaining_time":1.261172617},
{"learn":[0.664597024],"iteration":876,"passed_time":8.920376567,"remaining_time":1.251090442},
{"learn":[0.6632548803],"iteration":877,"passed_time":8.930679495,"remaining_time":1.240937242},
{"learn":[0.660838502],"iteration":878,"passed_time":8.942443801,"remaining_time":1.230984869},
{"learn":[0.6590440809],"iteration":879,"passed_time":8.9533501,"remaining_time":1.220911377},
{"learn":[0.6588406298],"iteration":880,"passed_time":8.964532736,"remaining_time":1.210873321},
{"learn":[0.658376561],"iteration":881,"passed_time":8.975094862,"remaining_time":1.200749653},
{"learn":[0.655509209],"iteration":882,"passed_time":8.986101595,"remaining_time":1.190683903},
{"learn":[0.6548316194],"iteration":883,"passed_time":8.996128855,"remaining_time":1.180487497},
{"learn":[0.6543507759],"iteration":884,"passed_time":9.006899117,"remaining_time":1.170388021},
{"learn":[0.6517253713],"iteration":885,"passed_time":9.01767375,"remaining_time":1.160287593},
{"learn":[0.6512556186],"iteration":886,"passed_time":9.029008839,"remaining_time":1.150257045},
{"learn":[0.6489420444],"iteration":887,"passed_time":9.03903377,"remaining_time":1.140058313},
{"learn":[0.6485254128],"iteration":888,"passed_time":9.049021543,"remaining_time":1.129855333},
{"learn":[0.6463632231],"iteration":889,"passed_time":9.059591188,"remaining_time":1.119724754},
{"learn":[0.6440824323],"iteration":890,"passed_time":9.069051121,"remaining_time":1.109457432},
{"learn":[0.6439130858],"iteration":891,"passed_time":9.079011521,"remaining_time":1.099252516},
{"learn":[0.6418330611],"iteration":892,"passed_time":9.088724464,"remaining_time":1.089018497},
{"learn":[0.6391657903],"iteration":893,"passed_time":9.098745067,"remaining_time":1.078822122},
{"learn":[0.6370831457],"iteration":894,"passed_time":9.109126687,"remaining_time":1.068668494},
{"learn":[0.6364768262],"iteration":895,"passed_time":9.11884947,"remaining_time":1.058437885},
{"learn":[0.6342793823],"iteration":896,"passed_time":9.129107146,"remaining_time":1.048269828},
{"learn":[0.634083497],"iteration":897,"passed_time":9.139693298,"remaining_time":1.038138882},
{"learn":[0.6316456796],"iteration":898,"passed_time":9.14971075,"remaining_time":1.027943032},
{"learn":[0.6293672144],"iteration":899,"passed_time":9.160744541,"remaining_time":1.017860505},
{"learn":[0.6268401362],"iteration":900,"passed_time":9.171962361,"remaining_time":1.007796086},
{"learn":[0.6245824776],"iteration":901,"passed_time":9.182410919,"remaining_time":0.9976455322},
{"learn":[0.6243256872],"iteration":902,"passed_time":9.192685804,"remaining_time":0.9874756622},
{"learn":[0.6240609079],"iteration":903,"passed_time":9.202810893,"remaining_time":0.9772896524},
{"learn":[0.6222122558],"iteration":904,"passed_time":9.21288136,"remaining_time":0.9670980434},
{"learn":[0.6197013232],"iteration":905,"passed_time":9.223475068,"remaining_time":0.9569609894},
{"learn":[0.6191336049],"iteration":906,"passed_time":9.234473485,"remaining_time":0.9468644257},
{"learn":[0.6172059555],"iteration":907,"passed_time":9.244026402,"remaining_time":0.9366194151},
{"learn":[0.6155908682],"iteration":908,"passed_time":9.253387243,"remaining_time":0.9263566987},
{"learn":[0.6142367114],"iteration":909,"passed_time":9.2627075,"remaining_time":0.9160919506},
{"learn":[0.6132770494],"iteration":910,"passed_time":9.27242607,"remaining_time":0.9058681891},
{"learn":[0.6119561457],"iteration":911,"passed_time":9.281842031,"remaining_time":0.8956163363},
{"learn":[0.6117415753],"iteration":912,"passed_time":9.291024704,"remaining_time":0.8853440846},
{"learn":[0.609836202],"iteration":913,"passed_time":9.301284793,"remaining_time":0.8751755932},
{"learn":[0.607478821],"iteration":914,"passed_time":9.310964169,"remaining_time":0.8649529556},
{"learn":[0.6045831758],"iteration":915,"passed_time":9.320949098,"remaining_time":0.8547595243},
{"learn":[0.6035245581],"iteration":916,"passed_time":9.330329025,"remaining_time":0.8445117874},
{"learn":[0.6017010686],"iteration":917,"passed_time":9.339743865,"remaining_time":0.8342690598},
{"learn":[0.5998776275],"iteration":918,"passed_time":9.351125019,"remaining_time":0.8242014434},
{"learn":[0.5975050658],"iteration":919,"passed_time":9.362206596,"remaining_time":0.8141049214},
{"learn":[0.5972520372],"iteration":920,"passed_time":9.373382874,"remaining_time":0.8040143833},
{"learn":[0.5960516859],"iteration":921,"passed_time":9.384021319,"remaining_time":0.7938759901},
{"learn":[0.5948870997],"iteration":922,"passed_time":9.394683381,"remaining_time":0.7837384836},
{"learn":[0.5932423516],"iteration":923,"passed_time":9.406882762,"remaining_time":0.7737262878},
{"learn":[0.5910626959],"iteration":924,"passed_time":9.41854893,"remaining_time":0.7636661294},
{"learn":[0.5892079343],"iteration":925,"passed_time":9.42950828,"remaining_time":0.753546018},
{"learn":[0.5873073766],"iteration":926,"passed_time":9.440231306,"remaining_time":0.7434054858},
{"learn":[0.584966565],"iteration":927,"passed_time":9.451840194,"remaining_time":0.7333324288},
{"learn":[0.5829713174],"iteration":928,"passed_time":9.462008862,"remaining_time":0.7231459949},
{"learn":[0.5817215296],"iteration":929,"passed_time":9.471563377,"remaining_time":0.7129133724},
{"learn":[0.5797335195],"iteration":930,"passed_time":9.481560721,"remaining_time":0.7027150266},
{"learn":[0.578890238],"iteration":931,"passed_time":9.491721776,"remaining_time":0.6925290567},
{"learn":[0.5773481752],"iteration":932,"passed_time":9.501965817,"remaining_time":0.6823490994},
{"learn":[0.5751658417],"iteration":933,"passed_time":9.511471931,"remaining_time":0.6721168602},
{"learn":[0.5729028291],"iteration":934,"passed_time":9.522573022,"remaining_time":0.661997055},
{"learn":[0.5724712522],"iteration":935,"passed_time":9.533021215,"remaining_time":0.6518305104},
{"learn":[0.570752299],"iteration":936,"passed_time":9.543707512,"remaining_time":0.6416793738},
{"learn":[0.5692206042],"iteration":937,"passed_time":9.554912348,"remaining_time":0.6315613705},
{"learn":[0.5687322832],"iteration":938,"passed_time":9.565819214,"remaining_time":0.6214216955},
{"learn":[0.5684085823],"iteration":939,"passed_time":9.576555186,"remaining_time":0.61126948},
{"learn":[0.566900134],"iteration":940,"passed_time":9.588005684,"remaining_time":0.601160824},
{"learn":[0.5662646462],"iteration":941,"passed_time":9.598887591,"remaining_time":0.5910143103},
{"learn":[0.5638233874],"iteration":942,"passed_time":9.60934507,"remaining_time":0.5808405822},
{"learn":[0.5632382972],"iteration":943,"passed_time":9.619876781,"remaining_time":0.5706706565},
{"learn":[0.5608935838],"iteration":944,"passed_time":9.630453199,"remaining_time":0.5605025671},
{"learn":[0.559486085],"iteration":945,"passed_time":9.641225372,"remaining_time":0.5503447887},
{"learn":[0.5590866374],"iteration":946,"passed_time":9.651012897,"remaining_time":0.5401306056},
{"learn":[0.5577813814],"iteration":947,"passed_time":9.66087078,"remaining_time":0.529921182},
{"learn":[0.5574016715],"iteration":948,"passed_time":9.670404087,"remaining_time":0.5196950563},
{"learn":[0.5558094784],"iteration":949,"passed_time":9.679786508,"remaining_time":0.5094624478},
{"learn":[0.5538003992],"iteration":950,"passed_time":9.689207666,"remaining_time":0.4992336231},
{"learn":[0.5519554929],"iteration":951,"passed_time":9.698576601,"remaining_time":0.4890038623},
{"learn":[0.5504162473],"iteration":952,"passed_time":9.708147818,"remaining_time":0.478785884},
{"learn":[0.5483035423],"iteration":953,"passed_time":9.717674792,"remaining_time":0.4685671284},
{"learn":[0.5463047613],"iteration":954,"passed_time":9.727585857,"remaining_time":0.45836792},
{"learn":[0.5449802019],"iteration":955,"passed_time":9.73784287,"remaining_time":0.4481852367},
{"learn":[0.5429231378],"iteration":956,"passed_time":9.747488255,"remaining_time":0.4379749164},
{"learn":[0.5421267146],"iteration":957,"passed_time":9.759896086,"remaining_time":0.4278868848},
{"learn":[0.5410052827],"iteration":958,"passed_time":9.772611106,"remaining_time":0.4178071484},
{"learn":[0.5391363043],"iteration":959,"passed_time":9.784816247,"remaining_time":0.4077006769},
{"learn":[0.5381577126],"iteration":960,"passed_time":9.797264638,"remaining_time":0.3975997095},
{"learn":[0.5358007752],"iteration":961,"passed_time":9.810787645,"remaining_time":0.3875363103},
{"learn":[0.5348166398],"iteration":962,"passed_time":9.823038344,"remaining_time":0.3774168419},
{"learn":[0.5330822578],"iteration":963,"passed_time":9.834541136,"remaining_time":0.3672650217},
{"learn":[0.531816349],"iteration":964,"passed_time":9.845945456,"remaining_time":0.35710683},
{"learn":[0.5303412105],"iteration":965,"passed_time":9.856745068,"remaining_time":0.3469247746},
{"learn":[0.528622982],"iteration":966,"passed_time":9.866589425,"remaining_time":0.3367088428},
{"learn":[0.5278031532],"iteration":967,"passed_time":9.876189089,"remaining_time":0.3264855897},
{"learn":[0.5259468082],"iteration":968,"passed_time":9.88562171,"remaining_time":0.3162582797},
{"learn":[0.5249316209],"iteration":969,"passed_time":9.895007766,"remaining_time":0.306031168},
{"learn":[0.5234723588],"iteration":970,"passed_time":9.906118109,"remaining_time":0.2958572865},
{"learn":[0.5222296002],"iteration":971,"passed_time":9.915768711,"remaining_time":0.2856394279},
{"learn":[0.5205728846],"iteration":972,"passed_time":9.925509424,"remaining_time":0.2754252358},
{"learn":[0.5185045416],"iteration":973,"passed_time":9.935172385,"remaining_time":0.2652099405},
{"learn":[0.5177417821],"iteration":974,"passed_time":9.944863101,"remaining_time":0.2549964898},
{"learn":[0.5158056258],"iteration":975,"passed_time":9.956013747,"remaining_time":0.2448200102},
{"learn":[0.5137083762],"iteration":976,"passed_time":9.968522809,"remaining_time":0.2346735155},
{"learn":[0.5132145516],"iteration":977,"passed_time":9.980826843,"remaining_time":0.2245175772},
{"learn":[0.51142615],"iteration":978,"passed_time":9.992372464,"remaining_time":0.2143409824},
{"learn":[0.5096087156],"iteration":979,"passed_time":10.00554855,"remaining_time":0.2041948684},
{"learn":[0.5081841265],"iteration":980,"passed_time":10.01871038,"remaining_time":0.1940423009},
{"learn":[0.5078879736],"iteration":981,"passed_time":10.03075594,"remaining_time":0.1838631436},
{"learn":[0.5074316378],"iteration":982,"passed_time":10.04307935,"remaining_time":0.1736849938},
{"learn":[0.5049459156],"iteration":983,"passed_time":10.05479318,"remaining_time":0.163492572},
{"learn":[0.5028828332],"iteration":984,"passed_time":10.06623267,"remaining_time":0.1532928833},
{"learn":[0.5027543007],"iteration":985,"passed_time":10.07755462,"remaining_time":0.1430890109},
{"learn":[0.5017645173],"iteration":986,"passed_time":10.08850993,"remaining_time":0.1328780436},
{"learn":[0.5000036646],"iteration":987,"passed_time":10.09988326,"remaining_time":0.1226706469},
{"learn":[0.4986096121],"iteration":988,"passed_time":10.11198937,"remaining_time":0.1124690425},
{"learn":[0.4973650258],"iteration":989,"passed_time":10.12332916,"remaining_time":0.1022558501},
{"learn":[0.4966275636],"iteration":990,"passed_time":10.13499924,"remaining_time":0.09204338359},
{"learn":[0.4962215562],"iteration":991,"passed_time":10.14618519,"remaining_time":0.08182407415},
{"learn":[0.4959745504],"iteration":992,"passed_time":10.15721684,"remaining_time":0.07160173002},
{"learn":[0.4949465596],"iteration":993,"passed_time":10.17012252,"remaining_time":0.06138906955},
{"learn":[0.4934948105],"iteration":994,"passed_time":10.18232908,"remaining_time":0.05116748283},
{"learn":[0.4921821452],"iteration":995,"passed_time":10.19501704,"remaining_time":0.04094384355},
{"learn":[0.491578335],"iteration":996,"passed_time":10.20816045,"remaining_time":0.03071663124},
{"learn":[0.4901770799],"iteration":997,"passed_time":10.21927159,"remaining_time":0.02047950219},
{"learn":[0.4888171876],"iteration":998,"passed_time":10.23085471,"remaining_time":0.0102410958},
{"learn":[0.4879275658],"iteration":999,"passed_time":10.24324205,"remaining_time":0}
]}